{"nodes": [{"name": "0", "group": 0}, {"name": "8", "group": 0}, {"name": "10", "group": 0}, {"name": "22", "group": 0}, {"name": "35", "group": 0}, {"name": "39", "group": 0}, {"name": "46", "group": 0}, {"name": "52", "group": 0}, {"name": "72", "group": 0}, {"name": "85", "group": 0}, {"name": "89", "group": 0}, {"name": "96", "group": 0}, {"name": "103", "group": 0}, {"name": "112", "group": 0}, {"name": "119", "group": 0}, {"name": "122", "group": 0}, {"name": "124", "group": 0}, {"name": "125", "group": 0}, {"name": "128", "group": 0}, {"name": "132", "group": 0}, {"name": "145", "group": 0}, {"name": "152", "group": 0}, {"name": "159", "group": 0}, {"name": "169", "group": 0}, {"name": "1", "group": 1}, {"name": "4", "group": 1}, {"name": "7", "group": 1}, {"name": "12", "group": 1}, {"name": "24", "group": 1}, {"name": "26", "group": 1}, {"name": "44", "group": 1}, {"name": "80", "group": 1}, {"name": "93", "group": 1}, {"name": "94", "group": 1}, {"name": "98", "group": 1}, {"name": "109", "group": 1}, {"name": "118", "group": 1}, {"name": "137", "group": 1}, {"name": "142", "group": 1}, {"name": "2", "group": 2}, {"name": "17", "group": 2}, {"name": "23", "group": 2}, {"name": "27", "group": 2}, {"name": "31", "group": 2}, {"name": "42", "group": 2}, {"name": "45", "group": 2}, {"name": "50", "group": 2}, {"name": "57", "group": 2}, {"name": "66", "group": 2}, {"name": "67", "group": 2}, {"name": "77", "group": 2}, {"name": "81", "group": 2}, {"name": "92", "group": 2}, {"name": "100", "group": 2}, {"name": "108", "group": 2}, {"name": "115", "group": 2}, {"name": "130", "group": 2}, {"name": "136", "group": 2}, {"name": "139", "group": 2}, {"name": "144", "group": 2}, {"name": "148", "group": 2}, {"name": "150", "group": 2}, {"name": "153", "group": 2}, {"name": "32", "group": 3}, {"name": "37", "group": 3}, {"name": "56", "group": 3}, {"name": "61", "group": 3}, {"name": "63", "group": 3}, {"name": "65", "group": 3}, {"name": "68", "group": 3}, {"name": "73", "group": 3}, {"name": "74", "group": 3}, {"name": "75", "group": 3}, {"name": "104", "group": 3}, {"name": "129", "group": 3}, {"name": "140", "group": 3}, {"name": "143", "group": 3}, {"name": "147", "group": 3}, {"name": "157", "group": 3}, {"name": "3", "group": 4}, {"name": "43", "group": 4}, {"name": "49", "group": 4}, {"name": "54", "group": 4}, {"name": "64", "group": 4}, {"name": "127", "group": 4}, {"name": "6", "group": 5}, {"name": "47", "group": 5}, {"name": "55", "group": 5}, {"name": "106", "group": 5}, {"name": "131", "group": 5}, {"name": "5", "group": 6}, {"name": "18", "group": 6}, {"name": "33", "group": 6}, {"name": "59", "group": 6}, {"name": "76", "group": 6}, {"name": "79", "group": 6}, {"name": "90", "group": 6}, {"name": "101", "group": 6}, {"name": "117", "group": 6}, {"name": "126", "group": 6}, {"name": "133", "group": 6}, {"name": "146", "group": 6}, {"name": "165", "group": 6}, {"name": "28", "group": 7}, {"name": "48", "group": 7}, {"name": "84", "group": 7}, {"name": "86", "group": 7}, {"name": "88", "group": 7}, {"name": "102", "group": 7}, {"name": "110", "group": 7}, {"name": "114", "group": 7}, {"name": "116", "group": 7}, {"name": "160", "group": 7}, {"name": "168", "group": 7}, {"name": "173", "group": 7}, {"name": "9", "group": 8}, {"name": "13", "group": 8}, {"name": "30", "group": 8}, {"name": "53", "group": 8}, {"name": "87", "group": 8}, {"name": "97", "group": 8}, {"name": "99", "group": 8}, {"name": "107", "group": 8}, {"name": "134", "group": 8}, {"name": "151", "group": 8}, {"name": "155", "group": 8}, {"name": "11", "group": 9}, {"name": "14", "group": 9}, {"name": "20", "group": 9}, {"name": "40", "group": 9}, {"name": "51", "group": 9}, {"name": "60", "group": 9}, {"name": "105", "group": 9}, {"name": "123", "group": 9}, {"name": "171", "group": 9}, {"name": "15", "group": 10}, {"name": "34", "group": 10}, {"name": "58", "group": 10}, {"name": "82", "group": 10}, {"name": "91", "group": 10}, {"name": "121", "group": 10}, {"name": "154", "group": 10}, {"name": "170", "group": 10}, {"name": "172", "group": 10}, {"name": "16", "group": 11}, {"name": "19", "group": 11}, {"name": "21", "group": 11}, {"name": "25", "group": 11}, {"name": "36", "group": 11}, {"name": "38", "group": 11}, {"name": "62", "group": 11}, {"name": "69", "group": 11}, {"name": "71", "group": 11}, {"name": "83", "group": 11}, {"name": "111", "group": 11}, {"name": "135", "group": 11}, {"name": "138", "group": 11}, {"name": "141", "group": 11}, {"name": "162", "group": 11}, {"name": "163", "group": 11}, {"name": "167", "group": 11}, {"name": "29", "group": 12}, {"name": "41", "group": 12}, {"name": "70", "group": 12}, {"name": "78", "group": 12}, {"name": "95", "group": 12}, {"name": "113", "group": 12}, {"name": "120", "group": 12}, {"name": "149", "group": 12}, {"name": "156", "group": 12}, {"name": "158", "group": 12}, {"name": "161", "group": 12}, {"name": "164", "group": 12}, {"name": "166", "group": 12}], "links": [{"source": 0, "target": 39, "value": 7}, {"source": 0, "target": 45, "value": 4}, {"source": 0, "target": 72, "value": 3}, {"source": 0, "target": 85, "value": 6}, {"source": 0, "target": 152, "value": 7}, {"source": 0, "target": 169, "value": 5}, {"source": 1, "target": 4, "value": 1}, {"source": 1, "target": 93, "value": 1}, {"source": 1, "target": 98, "value": 1}, {"source": 1, "target": 109, "value": 1}, {"source": 1, "target": 137, "value": 1}, {"source": 2, "target": 17, "value": 10000}, {"source": 2, "target": 67, "value": 10000}, {"source": 2, "target": 139, "value": 10000}, {"source": 2, "target": 144, "value": 10000}, {"source": 2, "target": 150, "value": 10000}, {"source": 2, "target": 153, "value": 10000}, {"source": 3, "target": 5, "value": 160}, {"source": 3, "target": 49, "value": 71}, {"source": 3, "target": 54, "value": 913}, {"source": 3, "target": 64, "value": 315}, {"source": 3, "target": 127, "value": 215}, {"source": 3, "target": 146, "value": 273}, {"source": 4, "target": 22, "value": 3}, {"source": 4, "target": 35, "value": 4}, {"source": 4, "target": 44, "value": 10}, {"source": 4, "target": 93, "value": 13}, {"source": 4, "target": 98, "value": 2}, {"source": 4, "target": 128, "value": 4}, {"source": 5, "target": 18, "value": 220}, {"source": 5, "target": 79, "value": 87}, {"source": 5, "target": 90, "value": 146}, {"source": 5, "target": 146, "value": 2891}, {"source": 6, "target": 47, "value": 2}, {"source": 6, "target": 55, "value": 3}, {"source": 6, "target": 89, "value": 1}, {"source": 6, "target": 106, "value": 8}, {"source": 6, "target": 131, "value": 4}, {"source": 7, "target": 12, "value": 1}, {"source": 7, "target": 24, "value": 3}, {"source": 7, "target": 26, "value": 8}, {"source": 7, "target": 80, "value": 3}, {"source": 7, "target": 94, "value": 5}, {"source": 7, "target": 109, "value": 2}, {"source": 7, "target": 118, "value": 2}, {"source": 7, "target": 137, "value": 3}, {"source": 7, "target": 142, "value": 141}, {"source": 8, "target": 10, "value": 2}, {"source": 8, "target": 35, "value": 3}, {"source": 8, "target": 89, "value": 3}, {"source": 8, "target": 128, "value": 3}, {"source": 8, "target": 132, "value": 2}, {"source": 8, "target": 173, "value": 1}, {"source": 9, "target": 53, "value": 5}, {"source": 9, "target": 87, "value": 3}, {"source": 9, "target": 117, "value": 2}, {"source": 9, "target": 134, "value": 2}, {"source": 9, "target": 151, "value": 5}, {"source": 10, "target": 35, "value": 6}, {"source": 10, "target": 72, "value": 3}, {"source": 10, "target": 89, "value": 11}, {"source": 10, "target": 128, "value": 7}, {"source": 10, "target": 132, "value": 7}, {"source": 10, "target": 145, "value": 76}, {"source": 11, "target": 14, "value": 6}, {"source": 11, "target": 20, "value": 25142}, {"source": 11, "target": 40, "value": 3722}, {"source": 11, "target": 51, "value": 2}, {"source": 11, "target": 60, "value": 911}, {"source": 11, "target": 105, "value": 58}, {"source": 11, "target": 123, "value": 587}, {"source": 11, "target": 171, "value": 911}, {"source": 12, "target": 24, "value": 2}, {"source": 12, "target": 80, "value": 1}, {"source": 12, "target": 118, "value": 1}, {"source": 12, "target": 142, "value": 1}, {"source": 13, "target": 98, "value": 3}, {"source": 13, "target": 107, "value": 2}, {"source": 13, "target": 109, "value": 3}, {"source": 13, "target": 137, "value": 2}, {"source": 13, "target": 155, "value": 2}, {"source": 14, "target": 20, "value": 6}, {"source": 14, "target": 40, "value": 6}, {"source": 14, "target": 104, "value": 8}, {"source": 14, "target": 105, "value": 7}, {"source": 14, "target": 132, "value": 4}, {"source": 15, "target": 34, "value": 4}, {"source": 15, "target": 46, "value": 3}, {"source": 15, "target": 58, "value": 21}, {"source": 15, "target": 82, "value": 7}, {"source": 15, "target": 91, "value": 2}, {"source": 15, "target": 121, "value": 3}, {"source": 15, "target": 154, "value": 4}, {"source": 15, "target": 172, "value": 2}, {"source": 16, "target": 19, "value": 165}, {"source": 16, "target": 36, "value": 44}, {"source": 16, "target": 71, "value": 150}, {"source": 16, "target": 111, "value": 19}, {"source": 16, "target": 138, "value": 36}, {"source": 16, "target": 162, "value": 23}, {"source": 16, "target": 167, "value": 33}, {"source": 17, "target": 23, "value": 10000}, {"source": 17, "target": 27, "value": 10000}, {"source": 17, "target": 31, "value": 10000}, {"source": 17, "target": 42, "value": 10000}, {"source": 17, "target": 45, "value": 6}, {"source": 17, "target": 50, "value": 10000}, {"source": 17, "target": 57, "value": 10000}, {"source": 17, "target": 66, "value": 10000}, {"source": 17, "target": 67, "value": 10000}, {"source": 17, "target": 77, "value": 10000}, {"source": 17, "target": 81, "value": 10000}, {"source": 17, "target": 100, "value": 10000}, {"source": 17, "target": 115, "value": 10000}, {"source": 17, "target": 130, "value": 10000}, {"source": 17, "target": 136, "value": 10000}, {"source": 17, "target": 139, "value": 10000}, {"source": 17, "target": 144, "value": 10000}, {"source": 17, "target": 148, "value": 10000}, {"source": 17, "target": 150, "value": 10000}, {"source": 17, "target": 153, "value": 10000}, {"source": 18, "target": 33, "value": 198}, {"source": 18, "target": 79, "value": 147}, {"source": 18, "target": 90, "value": 4268}, {"source": 18, "target": 117, "value": 166}, {"source": 18, "target": 146, "value": 135}, {"source": 19, "target": 36, "value": 64}, {"source": 19, "target": 71, "value": 2217}, {"source": 19, "target": 111, "value": 21}, {"source": 19, "target": 138, "value": 48}, {"source": 19, "target": 162, "value": 26}, {"source": 19, "target": 167, "value": 46}, {"source": 20, "target": 40, "value": 9832}, {"source": 20, "target": 51, "value": 2}, {"source": 20, "target": 60, "value": 1390}, {"source": 20, "target": 105, "value": 53}, {"source": 20, "target": 123, "value": 818}, {"source": 20, "target": 171, "value": 1390}, {"source": 21, "target": 25, "value": 2}, {"source": 21, "target": 38, "value": 2}, {"source": 21, "target": 62, "value": 4}, {"source": 21, "target": 69, "value": 3}, {"source": 21, "target": 83, "value": 2}, {"source": 21, "target": 141, "value": 5}, {"source": 22, "target": 35, "value": 4}, {"source": 22, "target": 44, "value": 8}, {"source": 22, "target": 52, "value": 16}, {"source": 22, "target": 96, "value": 14}, {"source": 22, "target": 103, "value": 8}, {"source": 22, "target": 112, "value": 4}, {"source": 22, "target": 119, "value": 9}, {"source": 22, "target": 122, "value": 25}, {"source": 22, "target": 159, "value": 4}, {"source": 23, "target": 67, "value": 10000}, {"source": 23, "target": 108, "value": 7}, {"source": 23, "target": 139, "value": 10000}, {"source": 23, "target": 144, "value": 10000}, {"source": 23, "target": 150, "value": 10000}, {"source": 23, "target": 153, "value": 10000}, {"source": 24, "target": 48, "value": 2}, {"source": 24, "target": 80, "value": 2}, {"source": 24, "target": 118, "value": 13}, {"source": 24, "target": 142, "value": 2}, {"source": 25, "target": 38, "value": 8}, {"source": 25, "target": 62, "value": 12}, {"source": 25, "target": 83, "value": 2}, {"source": 25, "target": 141, "value": 1}, {"source": 26, "target": 80, "value": 2}, {"source": 26, "target": 94, "value": 55}, {"source": 26, "target": 137, "value": 2}, {"source": 26, "target": 142, "value": 12}, {"source": 27, "target": 45, "value": 6}, {"source": 27, "target": 67, "value": 10000}, {"source": 27, "target": 135, "value": 79}, {"source": 27, "target": 139, "value": 10000}, {"source": 27, "target": 144, "value": 10000}, {"source": 27, "target": 150, "value": 10000}, {"source": 27, "target": 153, "value": 10000}, {"source": 27, "target": 163, "value": 79}, {"source": 28, "target": 52, "value": 1}, {"source": 28, "target": 86, "value": 1}, {"source": 28, "target": 92, "value": 6}, {"source": 28, "target": 122, "value": 1}, {"source": 28, "target": 124, "value": 5}, {"source": 29, "target": 41, "value": 591}, {"source": 29, "target": 70, "value": 27}, {"source": 29, "target": 78, "value": 51}, {"source": 29, "target": 120, "value": 151}, {"source": 29, "target": 156, "value": 250}, {"source": 29, "target": 158, "value": 40}, {"source": 30, "target": 53, "value": 1}, {"source": 30, "target": 97, "value": 3}, {"source": 30, "target": 99, "value": 2}, {"source": 30, "target": 107, "value": 2}, {"source": 30, "target": 134, "value": 2}, {"source": 31, "target": 67, "value": 10000}, {"source": 31, "target": 139, "value": 10000}, {"source": 31, "target": 144, "value": 10000}, {"source": 31, "target": 150, "value": 10000}, {"source": 31, "target": 153, "value": 10000}, {"source": 32, "target": 37, "value": 4188}, {"source": 32, "target": 65, "value": 10000}, {"source": 32, "target": 68, "value": 3}, {"source": 32, "target": 75, "value": 551}, {"source": 32, "target": 129, "value": 294114}, {"source": 32, "target": 140, "value": 1503}, {"source": 32, "target": 157, "value": 742}, {"source": 33, "target": 59, "value": 551}, {"source": 33, "target": 79, "value": 85}, {"source": 33, "target": 90, "value": 321}, {"source": 33, "target": 117, "value": 24276}, {"source": 33, "target": 126, "value": 1600}, {"source": 34, "target": 46, "value": 48}, {"source": 34, "target": 58, "value": 2}, {"source": 34, "target": 82, "value": 2}, {"source": 34, "target": 154, "value": 2}, {"source": 35, "target": 89, "value": 18}, {"source": 35, "target": 93, "value": 2}, {"source": 35, "target": 106, "value": 1}, {"source": 35, "target": 119, "value": 6}, {"source": 35, "target": 124, "value": 1}, {"source": 35, "target": 125, "value": 4}, {"source": 35, "target": 128, "value": 1445}, {"source": 36, "target": 71, "value": 93}, {"source": 36, "target": 135, "value": 103}, {"source": 36, "target": 138, "value": 2461}, {"source": 36, "target": 163, "value": 103}, {"source": 36, "target": 167, "value": 170}, {"source": 37, "target": 63, "value": 493}, {"source": 37, "target": 65, "value": 4188}, {"source": 37, "target": 68, "value": 3}, {"source": 37, "target": 74, "value": 552}, {"source": 37, "target": 104, "value": 4}, {"source": 37, "target": 129, "value": 3342}, {"source": 37, "target": 140, "value": 9350}, {"source": 37, "target": 157, "value": 2212}, {"source": 38, "target": 51, "value": 3}, {"source": 38, "target": 62, "value": 21}, {"source": 38, "target": 83, "value": 2}, {"source": 38, "target": 141, "value": 2}, {"source": 39, "target": 85, "value": 309}, {"source": 39, "target": 96, "value": 6}, {"source": 39, "target": 152, "value": 160}, {"source": 39, "target": 169, "value": 66}, {"source": 40, "target": 60, "value": 3571}, {"source": 40, "target": 105, "value": 46}, {"source": 40, "target": 123, "value": 1616}, {"source": 40, "target": 171, "value": 3571}, {"source": 41, "target": 70, "value": 18}, {"source": 41, "target": 78, "value": 103}, {"source": 41, "target": 120, "value": 619}, {"source": 41, "target": 156, "value": 92}, {"source": 41, "target": 158, "value": 72}, {"source": 42, "target": 67, "value": 10000}, {"source": 42, "target": 92, "value": 1}, {"source": 42, "target": 108, "value": 7}, {"source": 42, "target": 139, "value": 10000}, {"source": 42, "target": 144, "value": 10000}, {"source": 42, "target": 150, "value": 10000}, {"source": 42, "target": 153, "value": 10000}, {"source": 43, "target": 49, "value": 610}, {"source": 43, "target": 54, "value": 63}, {"source": 43, "target": 64, "value": 95}, {"source": 43, "target": 127, "value": 121}, {"source": 43, "target": 161, "value": 128}, {"source": 44, "target": 52, "value": 6}, {"source": 44, "target": 93, "value": 4}, {"source": 44, "target": 96, "value": 5}, {"source": 44, "target": 122, "value": 6}, {"source": 45, "target": 57, "value": 6}, {"source": 45, "target": 130, "value": 6}, {"source": 45, "target": 136, "value": 6}, {"source": 46, "target": 112, "value": 2}, {"source": 46, "target": 125, "value": 3}, {"source": 46, "target": 159, "value": 2}, {"source": 47, "target": 55, "value": 2}, {"source": 47, "target": 66, "value": 1}, {"source": 47, "target": 106, "value": 10}, {"source": 47, "target": 131, "value": 14}, {"source": 48, "target": 84, "value": 2}, {"source": 48, "target": 86, "value": 1}, {"source": 48, "target": 102, "value": 3}, {"source": 48, "target": 110, "value": 2}, {"source": 48, "target": 118, "value": 2}, {"source": 48, "target": 168, "value": 2}, {"source": 48, "target": 173, "value": 2}, {"source": 49, "target": 54, "value": 137}, {"source": 49, "target": 64, "value": 258}, {"source": 49, "target": 127, "value": 394}, {"source": 49, "target": 161, "value": 60}, {"source": 50, "target": 67, "value": 10000}, {"source": 50, "target": 139, "value": 10000}, {"source": 50, "target": 144, "value": 10000}, {"source": 50, "target": 150, "value": 10000}, {"source": 50, "target": 153, "value": 10000}, {"source": 51, "target": 56, "value": 5}, {"source": 51, "target": 105, "value": 2}, {"source": 52, "target": 85, "value": 7}, {"source": 52, "target": 96, "value": 1138}, {"source": 52, "target": 103, "value": 5}, {"source": 52, "target": 112, "value": 3}, {"source": 52, "target": 122, "value": 251}, {"source": 52, "target": 152, "value": 7}, {"source": 52, "target": 159, "value": 3}, {"source": 52, "target": 169, "value": 10}, {"source": 53, "target": 87, "value": 3}, {"source": 53, "target": 97, "value": 5}, {"source": 53, "target": 99, "value": 6}, {"source": 53, "target": 134, "value": 13}, {"source": 53, "target": 151, "value": 261}, {"source": 54, "target": 64, "value": 1855}, {"source": 54, "target": 127, "value": 808}, {"source": 54, "target": 146, "value": 114}, {"source": 55, "target": 106, "value": 3}, {"source": 55, "target": 122, "value": 1}, {"source": 55, "target": 131, "value": 2}, {"source": 56, "target": 61, "value": 4}, {"source": 56, "target": 63, "value": 4}, {"source": 56, "target": 73, "value": 4}, {"source": 56, "target": 143, "value": 4}, {"source": 57, "target": 67, "value": 10000}, {"source": 57, "target": 139, "value": 10000}, {"source": 57, "target": 144, "value": 10000}, {"source": 57, "target": 150, "value": 10000}, {"source": 57, "target": 153, "value": 10000}, {"source": 57, "target": 170, "value": 2}, {"source": 58, "target": 82, "value": 10}, {"source": 58, "target": 91, "value": 2}, {"source": 58, "target": 121, "value": 3}, {"source": 58, "target": 154, "value": 9}, {"source": 58, "target": 172, "value": 2}, {"source": 59, "target": 76, "value": 546}, {"source": 59, "target": 117, "value": 763}, {"source": 59, "target": 126, "value": 3220}, {"source": 59, "target": 165, "value": 939}, {"source": 60, "target": 75, "value": 303}, {"source": 60, "target": 105, "value": 37}, {"source": 60, "target": 123, "value": 15067}, {"source": 60, "target": 171, "value": 10000}, {"source": 61, "target": 63, "value": 152}, {"source": 61, "target": 73, "value": 1756}, {"source": 61, "target": 101, "value": 549}, {"source": 61, "target": 133, "value": 549}, {"source": 61, "target": 143, "value": 551}, {"source": 61, "target": 147, "value": 7}, {"source": 62, "target": 69, "value": 1}, {"source": 62, "target": 83, "value": 3}, {"source": 62, "target": 141, "value": 2}, {"source": 63, "target": 73, "value": 305}, {"source": 63, "target": 74, "value": 159271}, {"source": 63, "target": 140, "value": 830}, {"source": 63, "target": 143, "value": 675}, {"source": 63, "target": 157, "value": 1767}, {"source": 64, "target": 127, "value": 6984}, {"source": 65, "target": 75, "value": 551}, {"source": 65, "target": 129, "value": 294114}, {"source": 65, "target": 140, "value": 1503}, {"source": 65, "target": 157, "value": 742}, {"source": 66, "target": 67, "value": 10000}, {"source": 66, "target": 108, "value": 7}, {"source": 66, "target": 139, "value": 10000}, {"source": 66, "target": 144, "value": 10000}, {"source": 66, "target": 150, "value": 10000}, {"source": 66, "target": 153, "value": 10000}, {"source": 67, "target": 77, "value": 10000}, {"source": 67, "target": 81, "value": 10000}, {"source": 67, "target": 100, "value": 10000}, {"source": 67, "target": 108, "value": 7}, {"source": 67, "target": 115, "value": 10000}, {"source": 67, "target": 130, "value": 10000}, {"source": 67, "target": 136, "value": 10000}, {"source": 67, "target": 139, "value": 10000}, {"source": 67, "target": 144, "value": 10000}, {"source": 67, "target": 148, "value": 10000}, {"source": 67, "target": 150, "value": 10000}, {"source": 67, "target": 153, "value": 10000}, {"source": 68, "target": 140, "value": 3}, {"source": 68, "target": 147, "value": 19}, {"source": 68, "target": 157, "value": 3}, {"source": 68, "target": 160, "value": 2}, {"source": 69, "target": 111, "value": 1}, {"source": 69, "target": 141, "value": 41}, {"source": 69, "target": 162, "value": 1}, {"source": 70, "target": 111, "value": 81}, {"source": 70, "target": 156, "value": 59}, {"source": 70, "target": 162, "value": 57}, {"source": 71, "target": 111, "value": 17}, {"source": 71, "target": 138, "value": 65}, {"source": 71, "target": 162, "value": 21}, {"source": 71, "target": 167, "value": 60}, {"source": 72, "target": 103, "value": 10}, {"source": 72, "target": 119, "value": 7}, {"source": 72, "target": 145, "value": 3}, {"source": 73, "target": 74, "value": 280}, {"source": 73, "target": 101, "value": 226}, {"source": 73, "target": 133, "value": 226}, {"source": 73, "target": 143, "value": 2850}, {"source": 73, "target": 147, "value": 7}, {"source": 74, "target": 104, "value": 4}, {"source": 74, "target": 140, "value": 964}, {"source": 74, "target": 143, "value": 595}, {"source": 74, "target": 157, "value": 2207}, {"source": 75, "target": 123, "value": 412}, {"source": 75, "target": 129, "value": 602}, {"source": 76, "target": 101, "value": 393}, {"source": 76, "target": 126, "value": 274}, {"source": 76, "target": 133, "value": 393}, {"source": 76, "target": 165, "value": 9667}, {"source": 77, "target": 88, "value": 1}, {"source": 77, "target": 92, "value": 1}, {"source": 77, "target": 108, "value": 7}, {"source": 77, "target": 139, "value": 10000}, {"source": 77, "target": 144, "value": 10000}, {"source": 77, "target": 150, "value": 10000}, {"source": 77, "target": 153, "value": 10000}, {"source": 78, "target": 113, "value": 182}, {"source": 78, "target": 120, "value": 293}, {"source": 78, "target": 149, "value": 182}, {"source": 78, "target": 156, "value": 24}, {"source": 78, "target": 158, "value": 2787}, {"source": 78, "target": 164, "value": 182}, {"source": 79, "target": 90, "value": 142}, {"source": 79, "target": 117, "value": 79}, {"source": 80, "target": 94, "value": 1}, {"source": 80, "target": 109, "value": 3}, {"source": 80, "target": 137, "value": 2}, {"source": 80, "target": 142, "value": 3}, {"source": 81, "target": 92, "value": 1}, {"source": 81, "target": 139, "value": 10000}, {"source": 81, "target": 144, "value": 10000}, {"source": 81, "target": 150, "value": 10000}, {"source": 81, "target": 153, "value": 10000}, {"source": 82, "target": 91, "value": 2}, {"source": 82, "target": 121, "value": 15}, {"source": 82, "target": 154, "value": 4}, {"source": 82, "target": 170, "value": 3}, {"source": 82, "target": 172, "value": 7}, {"source": 83, "target": 141, "value": 1}, {"source": 84, "target": 86, "value": 1}, {"source": 84, "target": 102, "value": 3}, {"source": 84, "target": 110, "value": 9}, {"source": 84, "target": 114, "value": 1}, {"source": 84, "target": 116, "value": 3}, {"source": 84, "target": 168, "value": 3}, {"source": 85, "target": 96, "value": 8}, {"source": 85, "target": 152, "value": 586}, {"source": 85, "target": 169, "value": 227}, {"source": 86, "target": 88, "value": 2}, {"source": 86, "target": 168, "value": 1}, {"source": 86, "target": 173, "value": 1}, {"source": 87, "target": 105, "value": 2}, {"source": 87, "target": 134, "value": 2}, {"source": 87, "target": 151, "value": 3}, {"source": 88, "target": 108, "value": 4}, {"source": 88, "target": 160, "value": 2}, {"source": 88, "target": 168, "value": 2}, {"source": 89, "target": 124, "value": 1}, {"source": 89, "target": 125, "value": 4}, {"source": 89, "target": 128, "value": 19}, {"source": 89, "target": 132, "value": 5}, {"source": 89, "target": 145, "value": 6}, {"source": 90, "target": 117, "value": 258}, {"source": 90, "target": 126, "value": 153}, {"source": 90, "target": 146, "value": 97}, {"source": 91, "target": 121, "value": 2}, {"source": 91, "target": 172, "value": 2}, {"source": 92, "target": 124, "value": 8}, {"source": 93, "target": 98, "value": 3}, {"source": 93, "target": 137, "value": 4}, {"source": 94, "target": 137, "value": 2}, {"source": 94, "target": 142, "value": 8}, {"source": 95, "target": 113, "value": 207}, {"source": 95, "target": 149, "value": 207}, {"source": 95, "target": 161, "value": 238}, {"source": 95, "target": 164, "value": 207}, {"source": 95, "target": 166, "value": 10000}, {"source": 96, "target": 103, "value": 5}, {"source": 96, "target": 122, "value": 116}, {"source": 96, "target": 152, "value": 8}, {"source": 96, "target": 169, "value": 12}, {"source": 97, "target": 99, "value": 9}, {"source": 97, "target": 107, "value": 2}, {"source": 97, "target": 114, "value": 2}, {"source": 97, "target": 116, "value": 2}, {"source": 97, "target": 134, "value": 15}, {"source": 97, "target": 151, "value": 4}, {"source": 97, "target": 155, "value": 2}, {"source": 98, "target": 109, "value": 3}, {"source": 98, "target": 137, "value": 7}, {"source": 99, "target": 107, "value": 2}, {"source": 99, "target": 134, "value": 16}, {"source": 99, "target": 151, "value": 5}, {"source": 99, "target": 155, "value": 1}, {"source": 100, "target": 139, "value": 10000}, {"source": 100, "target": 144, "value": 10000}, {"source": 100, "target": 150, "value": 10000}, {"source": 100, "target": 153, "value": 10000}, {"source": 101, "target": 133, "value": 10000}, {"source": 101, "target": 147, "value": 7}, {"source": 101, "target": 165, "value": 272}, {"source": 102, "target": 110, "value": 4}, {"source": 102, "target": 160, "value": 2}, {"source": 102, "target": 168, "value": 8}, {"source": 102, "target": 173, "value": 2}, {"source": 103, "target": 119, "value": 18}, {"source": 104, "target": 132, "value": 3}, {"source": 104, "target": 140, "value": 4}, {"source": 104, "target": 157, "value": 4}, {"source": 105, "target": 131, "value": 1}, {"source": 105, "target": 171, "value": 37}, {"source": 106, "target": 131, "value": 16}, {"source": 107, "target": 134, "value": 2}, {"source": 107, "target": 155, "value": 49}, {"source": 109, "target": 137, "value": 3}, {"source": 110, "target": 114, "value": 2}, {"source": 110, "target": 116, "value": 6}, {"source": 110, "target": 168, "value": 2}, {"source": 110, "target": 173, "value": 1}, {"source": 111, "target": 162, "value": 2029}, {"source": 112, "target": 122, "value": 4}, {"source": 112, "target": 125, "value": 4}, {"source": 112, "target": 159, "value": 10000}, {"source": 113, "target": 149, "value": 10000}, {"source": 113, "target": 158, "value": 329}, {"source": 113, "target": 164, "value": 10000}, {"source": 113, "target": 166, "value": 207}, {"source": 114, "target": 116, "value": 2}, {"source": 114, "target": 134, "value": 1}, {"source": 115, "target": 139, "value": 10000}, {"source": 115, "target": 144, "value": 10000}, {"source": 115, "target": 150, "value": 10000}, {"source": 115, "target": 153, "value": 10000}, {"source": 115, "target": 170, "value": 2}, {"source": 116, "target": 134, "value": 2}, {"source": 117, "target": 126, "value": 2897}, {"source": 117, "target": 165, "value": 211}, {"source": 118, "target": 142, "value": 1}, {"source": 119, "target": 128, "value": 6}, {"source": 119, "target": 145, "value": 4}, {"source": 120, "target": 149, "value": 57}, {"source": 120, "target": 156, "value": 48}, {"source": 120, "target": 158, "value": 167}, {"source": 121, "target": 154, "value": 2}, {"source": 121, "target": 170, "value": 6}, {"source": 121, "target": 172, "value": 32}, {"source": 122, "target": 159, "value": 4}, {"source": 122, "target": 169, "value": 7}, {"source": 123, "target": 171, "value": 15067}, {"source": 124, "target": 128, "value": 1}, {"source": 125, "target": 128, "value": 4}, {"source": 125, "target": 159, "value": 4}, {"source": 126, "target": 165, "value": 396}, {"source": 128, "target": 145, "value": 4}, {"source": 129, "target": 140, "value": 1309}, {"source": 129, "target": 157, "value": 673}, {"source": 130, "target": 139, "value": 10000}, {"source": 130, "target": 144, "value": 10000}, {"source": 130, "target": 150, "value": 10000}, {"source": 130, "target": 153, "value": 10000}, {"source": 132, "target": 145, "value": 7}, {"source": 133, "target": 147, "value": 7}, {"source": 133, "target": 165, "value": 272}, {"source": 134, "target": 151, "value": 11}, {"source": 134, "target": 155, "value": 2}, {"source": 135, "target": 138, "value": 162}, {"source": 135, "target": 148, "value": 79}, {"source": 135, "target": 163, "value": 10000}, {"source": 135, "target": 167, "value": 65}, {"source": 136, "target": 139, "value": 10000}, {"source": 136, "target": 144, "value": 10000}, {"source": 136, "target": 150, "value": 10000}, {"source": 136, "target": 153, "value": 10000}, {"source": 137, "target": 142, "value": 2}, {"source": 138, "target": 163, "value": 162}, {"source": 138, "target": 167, "value": 160}, {"source": 139, "target": 144, "value": 10000}, {"source": 139, "target": 148, "value": 10000}, {"source": 139, "target": 150, "value": 10000}, {"source": 139, "target": 153, "value": 10000}, {"source": 140, "target": 157, "value": 8384}, {"source": 143, "target": 157, "value": 258}, {"source": 144, "target": 148, "value": 10000}, {"source": 144, "target": 150, "value": 10000}, {"source": 144, "target": 153, "value": 10000}, {"source": 147, "target": 160, "value": 1}, {"source": 148, "target": 150, "value": 10000}, {"source": 148, "target": 153, "value": 10000}, {"source": 148, "target": 163, "value": 79}, {"source": 149, "target": 158, "value": 329}, {"source": 149, "target": 164, "value": 10000}, {"source": 149, "target": 166, "value": 207}, {"source": 150, "target": 153, "value": 10000}, {"source": 152, "target": 169, "value": 219}, {"source": 158, "target": 164, "value": 329}, {"source": 160, "target": 168, "value": 5}, {"source": 161, "target": 164, "value": 56}, {"source": 161, "target": 166, "value": 238}, {"source": 163, "target": 167, "value": 65}, {"source": 164, "target": 166, "value": 207}, {"source": 170, "target": 172, "value": 17}]}