{"nodes": [{"name": "0", "group": 0}, {"name": "1", "group": 0}, {"name": "63", "group": 0}, {"name": "64", "group": 0}, {"name": "65", "group": 0}, {"name": "66", "group": 0}, {"name": "67", "group": 0}, {"name": "68", "group": 0}, {"name": "69", "group": 0}, {"name": "70", "group": 0}, {"name": "71", "group": 0}, {"name": "72", "group": 0}, {"name": "73", "group": 0}, {"name": "79", "group": 0}, {"name": "80", "group": 0}, {"name": "81", "group": 0}, {"name": "82", "group": 0}, {"name": "2", "group": 1}, {"name": "23", "group": 1}, {"name": "44", "group": 1}, {"name": "128", "group": 1}, {"name": "129", "group": 1}, {"name": "130", "group": 1}, {"name": "131", "group": 1}, {"name": "134", "group": 1}, {"name": "142", "group": 1}, {"name": "143", "group": 1}, {"name": "189", "group": 1}, {"name": "3", "group": 2}, {"name": "4", "group": 2}, {"name": "5", "group": 2}, {"name": "6", "group": 2}, {"name": "7", "group": 2}, {"name": "8", "group": 2}, {"name": "9", "group": 2}, {"name": "10", "group": 2}, {"name": "16", "group": 2}, {"name": "17", "group": 2}, {"name": "18", "group": 2}, {"name": "19", "group": 2}, {"name": "11", "group": 3}, {"name": "12", "group": 3}, {"name": "13", "group": 3}, {"name": "14", "group": 3}, {"name": "15", "group": 3}, {"name": "20", "group": 3}, {"name": "190", "group": 4}, {"name": "191", "group": 4}, {"name": "192", "group": 4}, {"name": "193", "group": 4}, {"name": "194", "group": 4}, {"name": "195", "group": 4}, {"name": "196", "group": 4}, {"name": "197", "group": 4}, {"name": "198", "group": 4}, {"name": "199", "group": 4}, {"name": "200", "group": 4}, {"name": "201", "group": 4}, {"name": "202", "group": 4}, {"name": "203", "group": 4}, {"name": "204", "group": 4}, {"name": "205", "group": 4}, {"name": "206", "group": 4}, {"name": "207", "group": 4}, {"name": "208", "group": 4}, {"name": "209", "group": 4}, {"name": "21", "group": 5}, {"name": "22", "group": 5}, {"name": "24", "group": 5}, {"name": "25", "group": 5}, {"name": "26", "group": 5}, {"name": "27", "group": 5}, {"name": "29", "group": 5}, {"name": "30", "group": 5}, {"name": "37", "group": 5}, {"name": "38", "group": 5}, {"name": "39", "group": 5}, {"name": "127", "group": 5}, {"name": "147", "group": 5}, {"name": "148", "group": 5}, {"name": "149", "group": 5}, {"name": "150", "group": 5}, {"name": "151", "group": 5}, {"name": "152", "group": 5}, {"name": "153", "group": 5}, {"name": "155", "group": 5}, {"name": "156", "group": 5}, {"name": "163", "group": 5}, {"name": "164", "group": 5}, {"name": "165", "group": 5}, {"name": "28", "group": 6}, {"name": "31", "group": 6}, {"name": "32", "group": 6}, {"name": "33", "group": 6}, {"name": "34", "group": 6}, {"name": "35", "group": 6}, {"name": "36", "group": 6}, {"name": "40", "group": 6}, {"name": "41", "group": 6}, {"name": "179", "group": 6}, {"name": "180", "group": 6}, {"name": "181", "group": 6}, {"name": "182", "group": 6}, {"name": "183", "group": 6}, {"name": "188", "group": 6}, {"name": "42", "group": 7}, {"name": "43", "group": 7}, {"name": "45", "group": 7}, {"name": "46", "group": 7}, {"name": "47", "group": 7}, {"name": "48", "group": 7}, {"name": "49", "group": 7}, {"name": "50", "group": 7}, {"name": "51", "group": 7}, {"name": "52", "group": 7}, {"name": "53", "group": 7}, {"name": "54", "group": 7}, {"name": "55", "group": 7}, {"name": "56", "group": 7}, {"name": "57", "group": 7}, {"name": "58", "group": 7}, {"name": "59", "group": 7}, {"name": "60", "group": 7}, {"name": "61", "group": 7}, {"name": "62", "group": 7}, {"name": "74", "group": 8}, {"name": "75", "group": 8}, {"name": "76", "group": 8}, {"name": "77", "group": 8}, {"name": "78", "group": 8}, {"name": "83", "group": 8}, {"name": "116", "group": 8}, {"name": "117", "group": 8}, {"name": "118", "group": 8}, {"name": "119", "group": 8}, {"name": "120", "group": 8}, {"name": "125", "group": 8}, {"name": "84", "group": 9}, {"name": "85", "group": 9}, {"name": "86", "group": 9}, {"name": "87", "group": 9}, {"name": "88", "group": 9}, {"name": "89", "group": 9}, {"name": "90", "group": 9}, {"name": "91", "group": 9}, {"name": "92", "group": 9}, {"name": "93", "group": 9}, {"name": "94", "group": 9}, {"name": "100", "group": 9}, {"name": "101", "group": 9}, {"name": "102", "group": 9}, {"name": "103", "group": 9}, {"name": "126", "group": 9}, {"name": "95", "group": 10}, {"name": "96", "group": 10}, {"name": "97", "group": 10}, {"name": "98", "group": 10}, {"name": "99", "group": 10}, {"name": "104", "group": 10}, {"name": "154", "group": 10}, {"name": "157", "group": 10}, {"name": "158", "group": 10}, {"name": "159", "group": 10}, {"name": "160", "group": 10}, {"name": "161", "group": 10}, {"name": "162", "group": 10}, {"name": "166", "group": 10}, {"name": "167", "group": 10}, {"name": "105", "group": 11}, {"name": "106", "group": 11}, {"name": "107", "group": 11}, {"name": "108", "group": 11}, {"name": "109", "group": 11}, {"name": "110", "group": 11}, {"name": "111", "group": 11}, {"name": "112", "group": 11}, {"name": "113", "group": 11}, {"name": "114", "group": 11}, {"name": "115", "group": 11}, {"name": "121", "group": 11}, {"name": "122", "group": 11}, {"name": "123", "group": 11}, {"name": "124", "group": 11}, {"name": "132", "group": 12}, {"name": "133", "group": 12}, {"name": "135", "group": 12}, {"name": "136", "group": 12}, {"name": "137", "group": 12}, {"name": "138", "group": 12}, {"name": "139", "group": 12}, {"name": "140", "group": 12}, {"name": "141", "group": 12}, {"name": "144", "group": 12}, {"name": "145", "group": 12}, {"name": "146", "group": 12}, {"name": "168", "group": 13}, {"name": "169", "group": 13}, {"name": "170", "group": 13}, {"name": "171", "group": 13}, {"name": "172", "group": 13}, {"name": "173", "group": 13}, {"name": "174", "group": 13}, {"name": "175", "group": 13}, {"name": "176", "group": 13}, {"name": "177", "group": 13}, {"name": "178", "group": 13}, {"name": "184", "group": 13}, {"name": "185", "group": 13}, {"name": "186", "group": 13}, {"name": "187", "group": 13}], "links": [{"source": 0, "target": 1, "value": 4}, {"source": 0, "target": 8, "value": 1}, {"source": 0, "target": 63, "value": 1}, {"source": 0, "target": 64, "value": 1}, {"source": 0, "target": 169, "value": 1}, {"source": 1, "target": 5, "value": 1}, {"source": 1, "target": 8, "value": 2}, {"source": 1, "target": 66, "value": 1}, {"source": 1, "target": 71, "value": 1}, {"source": 2, "target": 3, "value": 2}, {"source": 2, "target": 16, "value": 2}, {"source": 2, "target": 23, "value": 2}, {"source": 2, "target": 128, "value": 2}, {"source": 2, "target": 142, "value": 2}, {"source": 3, "target": 4, "value": 2}, {"source": 3, "target": 8, "value": 4}, {"source": 3, "target": 16, "value": 3}, {"source": 3, "target": 17, "value": 2}, {"source": 4, "target": 5, "value": 4}, {"source": 4, "target": 6, "value": 2}, {"source": 4, "target": 8, "value": 3}, {"source": 4, "target": 9, "value": 2}, {"source": 4, "target": 16, "value": 1}, {"source": 4, "target": 17, "value": 6}, {"source": 4, "target": 18, "value": 2}, {"source": 5, "target": 6, "value": 3}, {"source": 5, "target": 8, "value": 3}, {"source": 5, "target": 9, "value": 2}, {"source": 5, "target": 17, "value": 3}, {"source": 6, "target": 7, "value": 3}, {"source": 6, "target": 9, "value": 5}, {"source": 6, "target": 10, "value": 2}, {"source": 6, "target": 18, "value": 3}, {"source": 7, "target": 9, "value": 3}, {"source": 7, "target": 10, "value": 9}, {"source": 7, "target": 18, "value": 2}, {"source": 7, "target": 19, "value": 4}, {"source": 8, "target": 16, "value": 2}, {"source": 8, "target": 17, "value": 2}, {"source": 9, "target": 10, "value": 2}, {"source": 9, "target": 17, "value": 2}, {"source": 9, "target": 18, "value": 7}, {"source": 9, "target": 19, "value": 2}, {"source": 10, "target": 11, "value": 2}, {"source": 10, "target": 19, "value": 7}, {"source": 11, "target": 12, "value": 10}, {"source": 11, "target": 13, "value": 3}, {"source": 11, "target": 14, "value": 3}, {"source": 11, "target": 15, "value": 2}, {"source": 11, "target": 19, "value": 2}, {"source": 11, "target": 20, "value": 5}, {"source": 12, "target": 13, "value": 5}, {"source": 12, "target": 14, "value": 4}, {"source": 12, "target": 15, "value": 2}, {"source": 12, "target": 20, "value": 10}, {"source": 13, "target": 14, "value": 14}, {"source": 13, "target": 15, "value": 6}, {"source": 13, "target": 20, "value": 11}, {"source": 14, "target": 15, "value": 6}, {"source": 14, "target": 20, "value": 6}, {"source": 15, "target": 20, "value": 4}, {"source": 15, "target": 34, "value": 3}, {"source": 15, "target": 118, "value": 3}, {"source": 16, "target": 17, "value": 2}, {"source": 17, "target": 18, "value": 2}, {"source": 18, "target": 19, "value": 2}, {"source": 21, "target": 22, "value": 5}, {"source": 21, "target": 126, "value": 1}, {"source": 21, "target": 127, "value": 1}, {"source": 21, "target": 147, "value": 2}, {"source": 21, "target": 148, "value": 2}, {"source": 22, "target": 29, "value": 2}, {"source": 22, "target": 38, "value": 1}, {"source": 22, "target": 127, "value": 1}, {"source": 22, "target": 147, "value": 2}, {"source": 22, "target": 148, "value": 2}, {"source": 23, "target": 24, "value": 5}, {"source": 23, "target": 37, "value": 6}, {"source": 23, "target": 44, "value": 2}, {"source": 23, "target": 128, "value": 4}, {"source": 23, "target": 129, "value": 2}, {"source": 23, "target": 142, "value": 3}, {"source": 23, "target": 149, "value": 4}, {"source": 23, "target": 189, "value": 2}, {"source": 24, "target": 25, "value": 2}, {"source": 24, "target": 26, "value": 1}, {"source": 24, "target": 29, "value": 3}, {"source": 24, "target": 37, "value": 17}, {"source": 24, "target": 38, "value": 2}, {"source": 24, "target": 129, "value": 2}, {"source": 24, "target": 142, "value": 2}, {"source": 24, "target": 149, "value": 3}, {"source": 24, "target": 163, "value": 2}, {"source": 25, "target": 26, "value": 4}, {"source": 25, "target": 27, "value": 1}, {"source": 25, "target": 29, "value": 3}, {"source": 25, "target": 30, "value": 1}, {"source": 25, "target": 37, "value": 2}, {"source": 25, "target": 38, "value": 6}, {"source": 26, "target": 27, "value": 1}, {"source": 26, "target": 29, "value": 3}, {"source": 26, "target": 37, "value": 1}, {"source": 26, "target": 38, "value": 3}, {"source": 27, "target": 30, "value": 1}, {"source": 27, "target": 39, "value": 1}, {"source": 27, "target": 156, "value": 1}, {"source": 28, "target": 30, "value": 1}, {"source": 28, "target": 31, "value": 4}, {"source": 28, "target": 32, "value": 2}, {"source": 28, "target": 33, "value": 1}, {"source": 28, "target": 40, "value": 4}, {"source": 28, "target": 180, "value": 1}, {"source": 29, "target": 37, "value": 3}, {"source": 29, "target": 38, "value": 2}, {"source": 30, "target": 38, "value": 1}, {"source": 30, "target": 39, "value": 5}, {"source": 31, "target": 32, "value": 3}, {"source": 31, "target": 33, "value": 3}, {"source": 31, "target": 40, "value": 5}, {"source": 31, "target": 41, "value": 2}, {"source": 32, "target": 33, "value": 13}, {"source": 32, "target": 34, "value": 6}, {"source": 32, "target": 35, "value": 6}, {"source": 32, "target": 36, "value": 4}, {"source": 32, "target": 40, "value": 2}, {"source": 32, "target": 41, "value": 10}, {"source": 33, "target": 34, "value": 14}, {"source": 33, "target": 35, "value": 6}, {"source": 33, "target": 36, "value": 6}, {"source": 33, "target": 40, "value": 2}, {"source": 33, "target": 41, "value": 24}, {"source": 34, "target": 35, "value": 9}, {"source": 34, "target": 36, "value": 11}, {"source": 34, "target": 41, "value": 31}, {"source": 34, "target": 120, "value": 5}, {"source": 35, "target": 36, "value": 20}, {"source": 35, "target": 41, "value": 9}, {"source": 35, "target": 120, "value": 5}, {"source": 35, "target": 141, "value": 5}, {"source": 35, "target": 162, "value": 4}, {"source": 35, "target": 181, "value": 4}, {"source": 35, "target": 183, "value": 3}, {"source": 35, "target": 188, "value": 3}, {"source": 36, "target": 41, "value": 8}, {"source": 36, "target": 141, "value": 5}, {"source": 36, "target": 162, "value": 4}, {"source": 37, "target": 128, "value": 2}, {"source": 37, "target": 149, "value": 3}, {"source": 37, "target": 163, "value": 2}, {"source": 39, "target": 81, "value": 1}, {"source": 39, "target": 144, "value": 1}, {"source": 39, "target": 156, "value": 1}, {"source": 39, "target": 165, "value": 1}, {"source": 40, "target": 166, "value": 1}, {"source": 40, "target": 180, "value": 1}, {"source": 42, "target": 43, "value": 11}, {"source": 42, "target": 45, "value": 2}, {"source": 42, "target": 50, "value": 2}, {"source": 42, "target": 58, "value": 2}, {"source": 42, "target": 59, "value": 2}, {"source": 42, "target": 147, "value": 1}, {"source": 43, "target": 45, "value": 2}, {"source": 43, "target": 46, "value": 2}, {"source": 43, "target": 50, "value": 3}, {"source": 43, "target": 58, "value": 2}, {"source": 43, "target": 59, "value": 2}, {"source": 44, "target": 45, "value": 3}, {"source": 44, "target": 58, "value": 3}, {"source": 44, "target": 189, "value": 2}, {"source": 44, "target": 190, "value": 2}, {"source": 45, "target": 46, "value": 2}, {"source": 45, "target": 50, "value": 3}, {"source": 45, "target": 58, "value": 5}, {"source": 46, "target": 47, "value": 4}, {"source": 46, "target": 48, "value": 1}, {"source": 46, "target": 50, "value": 3}, {"source": 46, "target": 51, "value": 1}, {"source": 46, "target": 59, "value": 2}, {"source": 47, "target": 48, "value": 2}, {"source": 47, "target": 50, "value": 3}, {"source": 47, "target": 51, "value": 1}, {"source": 47, "target": 59, "value": 2}, {"source": 48, "target": 49, "value": 2}, {"source": 48, "target": 51, "value": 5}, {"source": 48, "target": 60, "value": 2}, {"source": 49, "target": 51, "value": 1}, {"source": 49, "target": 52, "value": 5}, {"source": 49, "target": 53, "value": 1}, {"source": 49, "target": 61, "value": 2}, {"source": 50, "target": 58, "value": 2}, {"source": 50, "target": 59, "value": 2}, {"source": 51, "target": 52, "value": 1}, {"source": 51, "target": 60, "value": 3}, {"source": 51, "target": 61, "value": 1}, {"source": 52, "target": 53, "value": 2}, {"source": 52, "target": 54, "value": 2}, {"source": 52, "target": 61, "value": 3}, {"source": 53, "target": 54, "value": 19}, {"source": 53, "target": 55, "value": 6}, {"source": 53, "target": 56, "value": 6}, {"source": 53, "target": 57, "value": 4}, {"source": 53, "target": 62, "value": 4}, {"source": 54, "target": 55, "value": 9}, {"source": 54, "target": 56, "value": 6}, {"source": 54, "target": 57, "value": 4}, {"source": 54, "target": 62, "value": 6}, {"source": 55, "target": 56, "value": 14}, {"source": 55, "target": 57, "value": 14}, {"source": 55, "target": 62, "value": 9}, {"source": 56, "target": 57, "value": 25}, {"source": 56, "target": 62, "value": 6}, {"source": 57, "target": 62, "value": 5}, {"source": 59, "target": 60, "value": 2}, {"source": 60, "target": 61, "value": 1}, {"source": 60, "target": 90, "value": 2}, {"source": 60, "target": 93, "value": 2}, {"source": 61, "target": 187, "value": 1}, {"source": 63, "target": 64, "value": 6}, {"source": 63, "target": 65, "value": 4}, {"source": 63, "target": 71, "value": 1}, {"source": 63, "target": 79, "value": 3}, {"source": 63, "target": 105, "value": 1}, {"source": 64, "target": 65, "value": 9}, {"source": 64, "target": 66, "value": 2}, {"source": 64, "target": 71, "value": 2}, {"source": 64, "target": 79, "value": 5}, {"source": 65, "target": 66, "value": 2}, {"source": 65, "target": 71, "value": 2}, {"source": 65, "target": 79, "value": 12}, {"source": 66, "target": 67, "value": 3}, {"source": 66, "target": 68, "value": 3}, {"source": 66, "target": 71, "value": 9}, {"source": 66, "target": 79, "value": 3}, {"source": 66, "target": 80, "value": 5}, {"source": 67, "target": 68, "value": 9}, {"source": 67, "target": 72, "value": 3}, {"source": 67, "target": 80, "value": 8}, {"source": 67, "target": 81, "value": 2}, {"source": 68, "target": 69, "value": 2}, {"source": 68, "target": 71, "value": 3}, {"source": 68, "target": 72, "value": 3}, {"source": 68, "target": 80, "value": 4}, {"source": 68, "target": 81, "value": 2}, {"source": 69, "target": 70, "value": 3}, {"source": 69, "target": 72, "value": 5}, {"source": 69, "target": 73, "value": 2}, {"source": 69, "target": 81, "value": 3}, {"source": 69, "target": 144, "value": 1}, {"source": 70, "target": 72, "value": 3}, {"source": 70, "target": 73, "value": 9}, {"source": 70, "target": 81, "value": 2}, {"source": 70, "target": 82, "value": 5}, {"source": 71, "target": 79, "value": 3}, {"source": 71, "target": 80, "value": 3}, {"source": 72, "target": 73, "value": 3}, {"source": 72, "target": 81, "value": 13}, {"source": 72, "target": 82, "value": 2}, {"source": 73, "target": 81, "value": 2}, {"source": 73, "target": 82, "value": 16}, {"source": 74, "target": 75, "value": 4}, {"source": 74, "target": 76, "value": 2}, {"source": 74, "target": 77, "value": 2}, {"source": 74, "target": 82, "value": 2}, {"source": 74, "target": 83, "value": 2}, {"source": 75, "target": 76, "value": 6}, {"source": 75, "target": 77, "value": 3}, {"source": 75, "target": 78, "value": 2}, {"source": 75, "target": 83, "value": 9}, {"source": 76, "target": 77, "value": 9}, {"source": 76, "target": 78, "value": 6}, {"source": 76, "target": 83, "value": 23}, {"source": 76, "target": 118, "value": 3}, {"source": 77, "target": 78, "value": 12}, {"source": 77, "target": 83, "value": 5}, {"source": 77, "target": 119, "value": 3}, {"source": 78, "target": 83, "value": 3}, {"source": 78, "target": 119, "value": 4}, {"source": 78, "target": 120, "value": 3}, {"source": 80, "target": 81, "value": 2}, {"source": 81, "target": 82, "value": 2}, {"source": 83, "target": 118, "value": 2}, {"source": 84, "target": 85, "value": 8}, {"source": 84, "target": 86, "value": 7}, {"source": 84, "target": 87, "value": 2}, {"source": 84, "target": 92, "value": 2}, {"source": 84, "target": 100, "value": 3}, {"source": 84, "target": 126, "value": 1}, {"source": 85, "target": 86, "value": 8}, {"source": 85, "target": 87, "value": 4}, {"source": 85, "target": 92, "value": 4}, {"source": 85, "target": 100, "value": 5}, {"source": 86, "target": 87, "value": 3}, {"source": 86, "target": 92, "value": 3}, {"source": 86, "target": 100, "value": 7}, {"source": 86, "target": 126, "value": 1}, {"source": 87, "target": 88, "value": 4}, {"source": 87, "target": 89, "value": 3}, {"source": 87, "target": 92, "value": 9}, {"source": 87, "target": 100, "value": 4}, {"source": 87, "target": 101, "value": 6}, {"source": 88, "target": 89, "value": 7}, {"source": 88, "target": 90, "value": 2}, {"source": 88, "target": 92, "value": 3}, {"source": 88, "target": 93, "value": 2}, {"source": 88, "target": 101, "value": 6}, {"source": 88, "target": 102, "value": 2}, {"source": 89, "target": 90, "value": 3}, {"source": 89, "target": 92, "value": 4}, {"source": 89, "target": 93, "value": 2}, {"source": 89, "target": 101, "value": 4}, {"source": 90, "target": 91, "value": 2}, {"source": 90, "target": 93, "value": 4}, {"source": 90, "target": 102, "value": 2}, {"source": 91, "target": 93, "value": 3}, {"source": 91, "target": 94, "value": 6}, {"source": 91, "target": 102, "value": 2}, {"source": 91, "target": 103, "value": 2}, {"source": 92, "target": 100, "value": 3}, {"source": 92, "target": 101, "value": 3}, {"source": 92, "target": 126, "value": 1}, {"source": 92, "target": 127, "value": 1}, {"source": 93, "target": 94, "value": 2}, {"source": 93, "target": 102, "value": 6}, {"source": 93, "target": 103, "value": 2}, {"source": 94, "target": 95, "value": 2}, {"source": 94, "target": 102, "value": 2}, {"source": 94, "target": 103, "value": 3}, {"source": 95, "target": 96, "value": 5}, {"source": 95, "target": 97, "value": 2}, {"source": 95, "target": 98, "value": 2}, {"source": 95, "target": 103, "value": 1}, {"source": 95, "target": 104, "value": 2}, {"source": 96, "target": 97, "value": 4}, {"source": 96, "target": 98, "value": 3}, {"source": 96, "target": 99, "value": 2}, {"source": 96, "target": 104, "value": 5}, {"source": 97, "target": 98, "value": 5}, {"source": 97, "target": 99, "value": 4}, {"source": 97, "target": 104, "value": 12}, {"source": 97, "target": 161, "value": 2}, {"source": 98, "target": 99, "value": 6}, {"source": 98, "target": 104, "value": 3}, {"source": 98, "target": 161, "value": 2}, {"source": 99, "target": 104, "value": 3}, {"source": 99, "target": 161, "value": 2}, {"source": 99, "target": 162, "value": 3}, {"source": 101, "target": 102, "value": 2}, {"source": 102, "target": 103, "value": 2}, {"source": 104, "target": 161, "value": 2}, {"source": 105, "target": 106, "value": 7}, {"source": 105, "target": 107, "value": 3}, {"source": 105, "target": 113, "value": 2}, {"source": 105, "target": 121, "value": 3}, {"source": 105, "target": 128, "value": 2}, {"source": 106, "target": 107, "value": 8}, {"source": 106, "target": 108, "value": 2}, {"source": 106, "target": 113, "value": 3}, {"source": 106, "target": 121, "value": 5}, {"source": 107, "target": 108, "value": 3}, {"source": 107, "target": 113, "value": 4}, {"source": 107, "target": 121, "value": 14}, {"source": 108, "target": 109, "value": 2}, {"source": 108, "target": 110, "value": 2}, {"source": 108, "target": 113, "value": 5}, {"source": 108, "target": 121, "value": 3}, {"source": 108, "target": 122, "value": 3}, {"source": 109, "target": 110, "value": 10}, {"source": 109, "target": 111, "value": 2}, {"source": 109, "target": 114, "value": 2}, {"source": 109, "target": 122, "value": 6}, {"source": 109, "target": 123, "value": 2}, {"source": 110, "target": 111, "value": 2}, {"source": 110, "target": 113, "value": 2}, {"source": 110, "target": 122, "value": 4}, {"source": 111, "target": 112, "value": 3}, {"source": 111, "target": 114, "value": 5}, {"source": 111, "target": 123, "value": 3}, {"source": 112, "target": 114, "value": 3}, {"source": 112, "target": 115, "value": 5}, {"source": 112, "target": 123, "value": 2}, {"source": 112, "target": 124, "value": 3}, {"source": 113, "target": 121, "value": 4}, {"source": 113, "target": 122, "value": 3}, {"source": 114, "target": 115, "value": 2}, {"source": 114, "target": 123, "value": 12}, {"source": 114, "target": 124, "value": 2}, {"source": 115, "target": 116, "value": 2}, {"source": 115, "target": 123, "value": 2}, {"source": 115, "target": 124, "value": 11}, {"source": 116, "target": 117, "value": 14}, {"source": 116, "target": 118, "value": 4}, {"source": 116, "target": 119, "value": 4}, {"source": 116, "target": 120, "value": 2}, {"source": 116, "target": 124, "value": 2}, {"source": 116, "target": 125, "value": 6}, {"source": 117, "target": 118, "value": 8}, {"source": 117, "target": 119, "value": 4}, {"source": 117, "target": 120, "value": 3}, {"source": 117, "target": 125, "value": 12}, {"source": 118, "target": 119, "value": 11}, {"source": 118, "target": 120, "value": 7}, {"source": 118, "target": 125, "value": 29}, {"source": 119, "target": 120, "value": 21}, {"source": 119, "target": 125, "value": 7}, {"source": 120, "target": 125, "value": 5}, {"source": 122, "target": 123, "value": 2}, {"source": 123, "target": 124, "value": 2}, {"source": 126, "target": 127, "value": 7}, {"source": 127, "target": 134, "value": 1}, {"source": 128, "target": 129, "value": 5}, {"source": 128, "target": 134, "value": 2}, {"source": 128, "target": 142, "value": 9}, {"source": 128, "target": 189, "value": 2}, {"source": 128, "target": 190, "value": 2}, {"source": 129, "target": 130, "value": 2}, {"source": 129, "target": 131, "value": 2}, {"source": 129, "target": 134, "value": 6}, {"source": 129, "target": 142, "value": 14}, {"source": 129, "target": 143, "value": 2}, {"source": 130, "target": 131, "value": 5}, {"source": 130, "target": 132, "value": 1}, {"source": 130, "target": 134, "value": 2}, {"source": 130, "target": 135, "value": 1}, {"source": 130, "target": 142, "value": 1}, {"source": 130, "target": 143, "value": 8}, {"source": 131, "target": 132, "value": 1}, {"source": 131, "target": 134, "value": 3}, {"source": 131, "target": 142, "value": 1}, {"source": 131, "target": 143, "value": 5}, {"source": 132, "target": 133, "value": 1}, {"source": 132, "target": 135, "value": 3}, {"source": 132, "target": 144, "value": 2}, {"source": 133, "target": 135, "value": 1}, {"source": 133, "target": 136, "value": 4}, {"source": 133, "target": 137, "value": 2}, {"source": 133, "target": 138, "value": 1}, {"source": 133, "target": 145, "value": 5}, {"source": 133, "target": 146, "value": 1}, {"source": 134, "target": 142, "value": 4}, {"source": 134, "target": 143, "value": 2}, {"source": 135, "target": 144, "value": 8}, {"source": 135, "target": 145, "value": 1}, {"source": 136, "target": 137, "value": 2}, {"source": 136, "target": 138, "value": 2}, {"source": 136, "target": 145, "value": 6}, {"source": 136, "target": 146, "value": 2}, {"source": 137, "target": 138, "value": 18}, {"source": 137, "target": 139, "value": 7}, {"source": 137, "target": 140, "value": 6}, {"source": 137, "target": 141, "value": 4}, {"source": 137, "target": 145, "value": 2}, {"source": 137, "target": 146, "value": 13}, {"source": 138, "target": 139, "value": 12}, {"source": 138, "target": 140, "value": 5}, {"source": 138, "target": 141, "value": 4}, {"source": 138, "target": 145, "value": 1}, {"source": 138, "target": 146, "value": 30}, {"source": 139, "target": 140, "value": 9}, {"source": 139, "target": 141, "value": 11}, {"source": 139, "target": 146, "value": 20}, {"source": 140, "target": 141, "value": 16}, {"source": 140, "target": 146, "value": 8}, {"source": 141, "target": 146, "value": 7}, {"source": 142, "target": 143, "value": 1}, {"source": 144, "target": 145, "value": 1}, {"source": 145, "target": 146, "value": 1}, {"source": 147, "target": 148, "value": 6}, {"source": 147, "target": 155, "value": 1}, {"source": 148, "target": 150, "value": 2}, {"source": 148, "target": 155, "value": 3}, {"source": 148, "target": 164, "value": 2}, {"source": 149, "target": 150, "value": 3}, {"source": 149, "target": 163, "value": 5}, {"source": 150, "target": 151, "value": 2}, {"source": 150, "target": 155, "value": 3}, {"source": 150, "target": 163, "value": 5}, {"source": 150, "target": 164, "value": 2}, {"source": 151, "target": 152, "value": 7}, {"source": 151, "target": 153, "value": 2}, {"source": 151, "target": 155, "value": 2}, {"source": 151, "target": 156, "value": 2}, {"source": 151, "target": 164, "value": 6}, {"source": 151, "target": 165, "value": 2}, {"source": 152, "target": 153, "value": 2}, {"source": 152, "target": 155, "value": 3}, {"source": 152, "target": 156, "value": 2}, {"source": 152, "target": 164, "value": 4}, {"source": 152, "target": 165, "value": 1}, {"source": 153, "target": 154, "value": 2}, {"source": 153, "target": 156, "value": 8}, {"source": 153, "target": 165, "value": 4}, {"source": 154, "target": 156, "value": 2}, {"source": 154, "target": 157, "value": 6}, {"source": 154, "target": 158, "value": 2}, {"source": 154, "target": 166, "value": 6}, {"source": 155, "target": 163, "value": 3}, {"source": 155, "target": 164, "value": 3}, {"source": 156, "target": 165, "value": 7}, {"source": 157, "target": 158, "value": 2}, {"source": 157, "target": 159, "value": 2}, {"source": 157, "target": 166, "value": 8}, {"source": 157, "target": 167, "value": 2}, {"source": 158, "target": 159, "value": 19}, {"source": 158, "target": 160, "value": 6}, {"source": 158, "target": 161, "value": 5}, {"source": 158, "target": 162, "value": 3}, {"source": 158, "target": 166, "value": 2}, {"source": 158, "target": 167, "value": 6}, {"source": 159, "target": 160, "value": 10}, {"source": 159, "target": 161, "value": 4}, {"source": 159, "target": 162, "value": 3}, {"source": 159, "target": 167, "value": 8}, {"source": 160, "target": 161, "value": 9}, {"source": 160, "target": 162, "value": 6}, {"source": 160, "target": 167, "value": 13}, {"source": 161, "target": 162, "value": 18}, {"source": 161, "target": 167, "value": 7}, {"source": 161, "target": 182, "value": 3}, {"source": 161, "target": 183, "value": 3}, {"source": 162, "target": 167, "value": 5}, {"source": 162, "target": 183, "value": 3}, {"source": 164, "target": 165, "value": 2}, {"source": 165, "target": 166, "value": 1}, {"source": 168, "target": 169, "value": 12}, {"source": 168, "target": 170, "value": 5}, {"source": 168, "target": 171, "value": 1}, {"source": 168, "target": 176, "value": 1}, {"source": 168, "target": 184, "value": 2}, {"source": 169, "target": 170, "value": 8}, {"source": 169, "target": 171, "value": 2}, {"source": 169, "target": 176, "value": 2}, {"source": 169, "target": 184, "value": 3}, {"source": 170, "target": 171, "value": 2}, {"source": 170, "target": 176, "value": 2}, {"source": 170, "target": 184, "value": 6}, {"source": 171, "target": 172, "value": 5}, {"source": 171, "target": 173, "value": 2}, {"source": 171, "target": 176, "value": 12}, {"source": 171, "target": 184, "value": 2}, {"source": 171, "target": 185, "value": 6}, {"source": 172, "target": 173, "value": 4}, {"source": 172, "target": 174, "value": 3}, {"source": 172, "target": 176, "value": 3}, {"source": 172, "target": 177, "value": 3}, {"source": 172, "target": 185, "value": 7}, {"source": 172, "target": 186, "value": 3}, {"source": 173, "target": 176, "value": 2}, {"source": 173, "target": 177, "value": 2}, {"source": 173, "target": 185, "value": 2}, {"source": 174, "target": 175, "value": 2}, {"source": 174, "target": 177, "value": 6}, {"source": 174, "target": 178, "value": 2}, {"source": 174, "target": 186, "value": 4}, {"source": 175, "target": 177, "value": 4}, {"source": 175, "target": 178, "value": 9}, {"source": 175, "target": 186, "value": 3}, {"source": 175, "target": 187, "value": 3}, {"source": 176, "target": 184, "value": 2}, {"source": 176, "target": 185, "value": 4}, {"source": 177, "target": 178, "value": 3}, {"source": 177, "target": 186, "value": 17}, {"source": 178, "target": 179, "value": 2}, {"source": 178, "target": 186, "value": 2}, {"source": 178, "target": 187, "value": 11}, {"source": 179, "target": 180, "value": 4}, {"source": 179, "target": 182, "value": 3}, {"source": 179, "target": 187, "value": 3}, {"source": 179, "target": 188, "value": 2}, {"source": 180, "target": 181, "value": 8}, {"source": 180, "target": 182, "value": 4}, {"source": 180, "target": 183, "value": 3}, {"source": 180, "target": 187, "value": 2}, {"source": 180, "target": 188, "value": 10}, {"source": 181, "target": 182, "value": 5}, {"source": 181, "target": 183, "value": 4}, {"source": 181, "target": 188, "value": 24}, {"source": 182, "target": 183, "value": 15}, {"source": 182, "target": 188, "value": 4}, {"source": 183, "target": 188, "value": 3}, {"source": 185, "target": 186, "value": 2}, {"source": 186, "target": 187, "value": 2}, {"source": 189, "target": 190, "value": 11}, {"source": 189, "target": 191, "value": 4}, {"source": 189, "target": 205, "value": 3}, {"source": 190, "target": 191, "value": 11}, {"source": 190, "target": 192, "value": 3}, {"source": 190, "target": 197, "value": 2}, {"source": 190, "target": 205, "value": 5}, {"source": 191, "target": 192, "value": 3}, {"source": 191, "target": 197, "value": 4}, {"source": 191, "target": 205, "value": 16}, {"source": 192, "target": 193, "value": 2}, {"source": 192, "target": 194, "value": 2}, {"source": 192, "target": 197, "value": 4}, {"source": 192, "target": 205, "value": 4}, {"source": 192, "target": 206, "value": 4}, {"source": 193, "target": 194, "value": 4}, {"source": 193, "target": 195, "value": 1}, {"source": 193, "target": 198, "value": 2}, {"source": 193, "target": 206, "value": 7}, {"source": 193, "target": 207, "value": 3}, {"source": 194, "target": 195, "value": 1}, {"source": 194, "target": 197, "value": 2}, {"source": 194, "target": 198, "value": 2}, {"source": 194, "target": 206, "value": 3}, {"source": 195, "target": 196, "value": 1}, {"source": 195, "target": 198, "value": 2}, {"source": 195, "target": 207, "value": 2}, {"source": 196, "target": 198, "value": 2}, {"source": 196, "target": 199, "value": 6}, {"source": 196, "target": 200, "value": 2}, {"source": 196, "target": 207, "value": 2}, {"source": 196, "target": 208, "value": 3}, {"source": 197, "target": 205, "value": 4}, {"source": 197, "target": 206, "value": 3}, {"source": 198, "target": 199, "value": 2}, {"source": 198, "target": 207, "value": 7}, {"source": 199, "target": 200, "value": 3}, {"source": 199, "target": 201, "value": 2}, {"source": 199, "target": 207, "value": 2}, {"source": 199, "target": 208, "value": 8}, {"source": 200, "target": 201, "value": 13}, {"source": 200, "target": 202, "value": 7}, {"source": 200, "target": 203, "value": 6}, {"source": 200, "target": 204, "value": 5}, {"source": 200, "target": 208, "value": 3}, {"source": 200, "target": 209, "value": 9}, {"source": 201, "target": 202, "value": 8}, {"source": 201, "target": 203, "value": 8}, {"source": 201, "target": 204, "value": 6}, {"source": 201, "target": 208, "value": 3}, {"source": 201, "target": 209, "value": 19}, {"source": 202, "target": 203, "value": 7}, {"source": 202, "target": 204, "value": 6}, {"source": 202, "target": 209, "value": 10}, {"source": 203, "target": 204, "value": 32}, {"source": 203, "target": 209, "value": 12}, {"source": 204, "target": 209, "value": 9}, {"source": 205, "target": 206, "value": 2}, {"source": 206, "target": 207, "value": 2}, {"source": 208, "target": 209, "value": 2}]}