{"nodes": [{"name": "obj_0", "group": 0}, {"name": "obj_2", "group": 0}, {"name": "obj_59", "group": 0}, {"name": "obj_86", "group": 0}, {"name": "obj_87", "group": 0}, {"name": "obj_108", "group": 0}, {"name": "obj_122", "group": 0}, {"name": "obj_123", "group": 0}, {"name": "obj_128", "group": 0}, {"name": "obj_164", "group": 0}, {"name": "obj_170", "group": 0}, {"name": "obj_184", "group": 0}, {"name": "obj_192", "group": 0}, {"name": "obj_193", "group": 0}, {"name": "obj_205", "group": 0}, {"name": "obj_206", "group": 0}, {"name": "obj_1", "group": 1}, {"name": "obj_28", "group": 1}, {"name": "obj_44", "group": 1}, {"name": "obj_47", "group": 1}, {"name": "obj_66", "group": 1}, {"name": "obj_67", "group": 1}, {"name": "obj_100", "group": 1}, {"name": "obj_107", "group": 1}, {"name": "obj_121", "group": 1}, {"name": "obj_131", "group": 1}, {"name": "obj_132", "group": 1}, {"name": "obj_133", "group": 1}, {"name": "obj_134", "group": 1}, {"name": "obj_163", "group": 1}, {"name": "obj_191", "group": 1}, {"name": "obj_13", "group": 2}, {"name": "obj_15", "group": 2}, {"name": "obj_20", "group": 2}, {"name": "obj_53", "group": 2}, {"name": "obj_54", "group": 2}, {"name": "obj_55", "group": 2}, {"name": "obj_56", "group": 2}, {"name": "obj_77", "group": 2}, {"name": "obj_92", "group": 2}, {"name": "obj_97", "group": 2}, {"name": "obj_98", "group": 2}, {"name": "obj_112", "group": 2}, {"name": "obj_116", "group": 2}, {"name": "obj_137", "group": 2}, {"name": "obj_174", "group": 2}, {"name": "obj_175", "group": 2}, {"name": "obj_179", "group": 2}, {"name": "obj_181", "group": 2}, {"name": "obj_182", "group": 2}, {"name": "obj_202", "group": 2}, {"name": "obj_203", "group": 2}, {"name": "obj_3", "group": 3}, {"name": "obj_8", "group": 3}, {"name": "obj_16", "group": 3}, {"name": "obj_60", "group": 3}, {"name": "obj_68", "group": 3}, {"name": "obj_69", "group": 3}, {"name": "obj_71", "group": 3}, {"name": "obj_103", "group": 3}, {"name": "obj_104", "group": 3}, {"name": "obj_135", "group": 3}, {"name": "obj_144", "group": 3}, {"name": "obj_145", "group": 3}, {"name": "obj_151", "group": 3}, {"name": "obj_156", "group": 3}, {"name": "obj_157", "group": 3}, {"name": "obj_166", "group": 3}, {"name": "obj_171", "group": 3}, {"name": "obj_172", "group": 3}, {"name": "obj_185", "group": 3}, {"name": "obj_186", "group": 3}, {"name": "obj_22", "group": 4}, {"name": "obj_26", "group": 4}, {"name": "obj_27", "group": 4}, {"name": "obj_29", "group": 4}, {"name": "obj_101", "group": 4}, {"name": "obj_102", "group": 4}, {"name": "obj_194", "group": 4}, {"name": "obj_195", "group": 4}, {"name": "obj_196", "group": 4}, {"name": "obj_197", "group": 4}, {"name": "obj_7", "group": 5}, {"name": "obj_11", "group": 5}, {"name": "obj_21", "group": 5}, {"name": "obj_23", "group": 5}, {"name": "obj_30", "group": 5}, {"name": "obj_31", "group": 5}, {"name": "obj_32", "group": 5}, {"name": "obj_33", "group": 5}, {"name": "obj_34", "group": 5}, {"name": "obj_35", "group": 5}, {"name": "obj_40", "group": 5}, {"name": "obj_41", "group": 5}, {"name": "obj_42", "group": 5}, {"name": "obj_43", "group": 5}, {"name": "obj_50", "group": 5}, {"name": "obj_65", "group": 5}, {"name": "obj_73", "group": 5}, {"name": "obj_78", "group": 5}, {"name": "obj_80", "group": 5}, {"name": "obj_83", "group": 5}, {"name": "obj_105", "group": 5}, {"name": "obj_120", "group": 5}, {"name": "obj_126", "group": 5}, {"name": "obj_127", "group": 5}, {"name": "obj_147", "group": 5}, {"name": "obj_150", "group": 5}, {"name": "obj_155", "group": 5}, {"name": "obj_189", "group": 5}, {"name": "obj_200", "group": 5}, {"name": "obj_6", "group": 6}, {"name": "obj_9", "group": 6}, {"name": "obj_10", "group": 6}, {"name": "obj_18", "group": 6}, {"name": "obj_19", "group": 6}, {"name": "obj_89", "group": 6}, {"name": "obj_115", "group": 6}, {"name": "obj_124", "group": 6}, {"name": "obj_177", "group": 6}, {"name": "obj_187", "group": 6}, {"name": "obj_5", "group": 7}, {"name": "obj_24", "group": 7}, {"name": "obj_49", "group": 7}, {"name": "obj_79", "group": 7}, {"name": "obj_82", "group": 7}, {"name": "obj_113", "group": 7}, {"name": "obj_136", "group": 7}, {"name": "obj_173", "group": 7}, {"name": "obj_190", "group": 7}, {"name": "obj_25", "group": 8}, {"name": "obj_37", "group": 8}, {"name": "obj_38", "group": 8}, {"name": "obj_39", "group": 8}, {"name": "obj_46", "group": 8}, {"name": "obj_48", "group": 8}, {"name": "obj_58", "group": 8}, {"name": "obj_95", "group": 8}, {"name": "obj_106", "group": 8}, {"name": "obj_110", "group": 8}, {"name": "obj_148", "group": 8}, {"name": "obj_153", "group": 8}, {"name": "obj_176", "group": 8}, {"name": "obj_12", "group": 9}, {"name": "obj_70", "group": 9}, {"name": "obj_74", "group": 9}, {"name": "obj_90", "group": 9}, {"name": "obj_91", "group": 9}, {"name": "obj_99", "group": 9}, {"name": "obj_138", "group": 9}, {"name": "obj_139", "group": 9}, {"name": "obj_146", "group": 9}, {"name": "obj_159", "group": 9}, {"name": "obj_167", "group": 9}, {"name": "obj_178", "group": 9}, {"name": "obj_180", "group": 9}, {"name": "obj_14", "group": 10}, {"name": "obj_36", "group": 10}, {"name": "obj_45", "group": 10}, {"name": "obj_57", "group": 10}, {"name": "obj_63", "group": 10}, {"name": "obj_64", "group": 10}, {"name": "obj_75", "group": 10}, {"name": "obj_76", "group": 10}, {"name": "obj_84", "group": 10}, {"name": "obj_85", "group": 10}, {"name": "obj_96", "group": 10}, {"name": "obj_109", "group": 10}, {"name": "obj_111", "group": 10}, {"name": "obj_119", "group": 10}, {"name": "obj_140", "group": 10}, {"name": "obj_141", "group": 10}, {"name": "obj_149", "group": 10}, {"name": "obj_152", "group": 10}, {"name": "obj_154", "group": 10}, {"name": "obj_158", "group": 10}, {"name": "obj_160", "group": 10}, {"name": "obj_161", "group": 10}, {"name": "obj_162", "group": 10}, {"name": "obj_168", "group": 10}, {"name": "obj_169", "group": 10}, {"name": "obj_183", "group": 10}, {"name": "obj_199", "group": 10}, {"name": "obj_201", "group": 10}, {"name": "obj_204", "group": 10}, {"name": "obj_209", "group": 10}, {"name": "obj_4", "group": 11}, {"name": "obj_17", "group": 11}, {"name": "obj_51", "group": 11}, {"name": "obj_52", "group": 11}, {"name": "obj_61", "group": 11}, {"name": "obj_62", "group": 11}, {"name": "obj_72", "group": 11}, {"name": "obj_81", "group": 11}, {"name": "obj_88", "group": 11}, {"name": "obj_93", "group": 11}, {"name": "obj_94", "group": 11}, {"name": "obj_114", "group": 11}, {"name": "obj_117", "group": 11}, {"name": "obj_118", "group": 11}, {"name": "obj_125", "group": 11}, {"name": "obj_129", "group": 11}, {"name": "obj_130", "group": 11}, {"name": "obj_142", "group": 11}, {"name": "obj_143", "group": 11}, {"name": "obj_165", "group": 11}, {"name": "obj_188", "group": 11}, {"name": "obj_198", "group": 11}, {"name": "obj_207", "group": 11}, {"name": "obj_208", "group": 11}, {"name": "obj_0", "group": 0}, {"name": "obj_2", "group": 0}, {"name": "obj_44", "group": 0}, {"name": "obj_86", "group": 0}, {"name": "obj_87", "group": 0}, {"name": "obj_107", "group": 0}, {"name": "obj_108", "group": 0}, {"name": "obj_121", "group": 0}, {"name": "obj_122", "group": 0}, {"name": "obj_123", "group": 0}, {"name": "obj_134", "group": 0}, {"name": "obj_164", "group": 0}, {"name": "obj_170", "group": 0}, {"name": "obj_184", "group": 0}, {"name": "obj_191", "group": 0}, {"name": "obj_192", "group": 0}, {"name": "obj_193", "group": 0}, {"name": "obj_205", "group": 0}, {"name": "obj_206", "group": 0}, {"name": "obj_207", "group": 0}, {"name": "obj_5", "group": 1}, {"name": "obj_7", "group": 1}, {"name": "obj_42", "group": 1}, {"name": "obj_43", "group": 1}, {"name": "obj_45", "group": 1}, {"name": "obj_47", "group": 1}, {"name": "obj_50", "group": 1}, {"name": "obj_58", "group": 1}, {"name": "obj_84", "group": 1}, {"name": "obj_85", "group": 1}, {"name": "obj_92", "group": 1}, {"name": "obj_100", "group": 1}, {"name": "obj_109", "group": 1}, {"name": "obj_110", "group": 1}, {"name": "obj_112", "group": 1}, {"name": "obj_113", "group": 1}, {"name": "obj_131", "group": 1}, {"name": "obj_152", "group": 1}, {"name": "obj_173", "group": 1}, {"name": "obj_175", "group": 1}, {"name": "obj_189", "group": 1}, {"name": "obj_190", "group": 1}, {"name": "obj_3", "group": 2}, {"name": "obj_8", "group": 2}, {"name": "obj_16", "group": 2}, {"name": "obj_68", "group": 2}, {"name": "obj_69", "group": 2}, {"name": "obj_71", "group": 2}, {"name": "obj_103", "group": 2}, {"name": "obj_135", "group": 2}, {"name": "obj_144", "group": 2}, {"name": "obj_145", "group": 2}, {"name": "obj_151", "group": 2}, {"name": "obj_156", "group": 2}, {"name": "obj_157", "group": 2}, {"name": "obj_166", "group": 2}, {"name": "obj_185", "group": 2}, {"name": "obj_186", "group": 2}, {"name": "obj_4", "group": 3}, {"name": "obj_6", "group": 3}, {"name": "obj_17", "group": 3}, {"name": "obj_51", "group": 3}, {"name": "obj_52", "group": 3}, {"name": "obj_61", "group": 3}, {"name": "obj_62", "group": 3}, {"name": "obj_72", "group": 3}, {"name": "obj_81", "group": 3}, {"name": "obj_94", "group": 3}, {"name": "obj_114", "group": 3}, {"name": "obj_117", "group": 3}, {"name": "obj_129", "group": 3}, {"name": "obj_130", "group": 3}, {"name": "obj_143", "group": 3}, {"name": "obj_188", "group": 3}, {"name": "obj_198", "group": 3}, {"name": "obj_208", "group": 3}, {"name": "obj_27", "group": 4}, {"name": "obj_46", "group": 4}, {"name": "obj_48", "group": 4}, {"name": "obj_59", "group": 4}, {"name": "obj_60", "group": 4}, {"name": "obj_88", "group": 4}, {"name": "obj_89", "group": 4}, {"name": "obj_90", "group": 4}, {"name": "obj_91", "group": 4}, {"name": "obj_93", "group": 4}, {"name": "obj_126", "group": 4}, {"name": "obj_127", "group": 4}, {"name": "obj_147", "group": 4}, {"name": "obj_148", "group": 4}, {"name": "obj_154", "group": 4}, {"name": "obj_155", "group": 4}, {"name": "obj_165", "group": 4}, {"name": "obj_9", "group": 5}, {"name": "obj_10", "group": 5}, {"name": "obj_18", "group": 5}, {"name": "obj_19", "group": 5}, {"name": "obj_115", "group": 5}, {"name": "obj_124", "group": 5}, {"name": "obj_177", "group": 5}, {"name": "obj_187", "group": 5}, {"name": "obj_49", "group": 6}, {"name": "obj_53", "group": 6}, {"name": "obj_55", "group": 6}, {"name": "obj_96", "group": 6}, {"name": "obj_111", "group": 6}, {"name": "obj_132", "group": 6}, {"name": "obj_136", "group": 6}, {"name": "obj_153", "group": 6}, {"name": "obj_158", "group": 6}, {"name": "obj_200", "group": 6}, {"name": "obj_12", "group": 7}, {"name": "obj_13", "group": 7}, {"name": "obj_15", "group": 7}, {"name": "obj_20", "group": 7}, {"name": "obj_57", "group": 7}, {"name": "obj_76", "group": 7}, {"name": "obj_83", "group": 7}, {"name": "obj_95", "group": 7}, {"name": "obj_118", "group": 7}, {"name": "obj_119", "group": 7}, {"name": "obj_120", "group": 7}, {"name": "obj_133", "group": 7}, {"name": "obj_137", "group": 7}, {"name": "obj_140", "group": 7}, {"name": "obj_160", "group": 7}, {"name": "obj_181", "group": 7}, {"name": "obj_182", "group": 7}, {"name": "obj_183", "group": 7}, {"name": "obj_204", "group": 7}, {"name": "obj_1", "group": 8}, {"name": "obj_21", "group": 8}, {"name": "obj_22", "group": 8}, {"name": "obj_23", "group": 8}, {"name": "obj_24", "group": 8}, {"name": "obj_25", "group": 8}, {"name": "obj_28", "group": 8}, {"name": "obj_30", "group": 8}, {"name": "obj_31", "group": 8}, {"name": "obj_37", "group": 8}, {"name": "obj_38", "group": 8}, {"name": "obj_39", "group": 8}, {"name": "obj_40", "group": 8}, {"name": "obj_64", "group": 8}, {"name": "obj_101", "group": 8}, {"name": "obj_102", "group": 8}, {"name": "obj_128", "group": 8}, {"name": "obj_142", "group": 8}, {"name": "obj_163", "group": 8}, {"name": "obj_168", "group": 8}, {"name": "obj_169", "group": 8}, {"name": "obj_171", "group": 8}, {"name": "obj_172", "group": 8}, {"name": "obj_174", "group": 8}, {"name": "obj_176", "group": 8}, {"name": "obj_26", "group": 9}, {"name": "obj_29", "group": 9}, {"name": "obj_194", "group": 9}, {"name": "obj_195", "group": 9}, {"name": "obj_196", "group": 9}, {"name": "obj_197", "group": 9}, {"name": "obj_11", "group": 10}, {"name": "obj_14", "group": 10}, {"name": "obj_32", "group": 10}, {"name": "obj_33", "group": 10}, {"name": "obj_34", "group": 10}, {"name": "obj_35", "group": 10}, {"name": "obj_36", "group": 10}, {"name": "obj_41", "group": 10}, {"name": "obj_54", "group": 10}, {"name": "obj_56", "group": 10}, {"name": "obj_97", "group": 10}, {"name": "obj_98", "group": 10}, {"name": "obj_104", "group": 10}, {"name": "obj_105", "group": 10}, {"name": "obj_106", "group": 10}, {"name": "obj_116", "group": 10}, {"name": "obj_125", "group": 10}, {"name": "obj_141", "group": 10}, {"name": "obj_149", "group": 10}, {"name": "obj_150", "group": 10}, {"name": "obj_161", "group": 10}, {"name": "obj_162", "group": 10}, {"name": "obj_179", "group": 10}, {"name": "obj_199", "group": 10}, {"name": "obj_201", "group": 10}, {"name": "obj_202", "group": 10}, {"name": "obj_203", "group": 10}, {"name": "obj_209", "group": 10}, {"name": "obj_70", "group": 11}, {"name": "obj_74", "group": 11}, {"name": "obj_99", "group": 11}, {"name": "obj_138", "group": 11}, {"name": "obj_139", "group": 11}, {"name": "obj_146", "group": 11}, {"name": "obj_159", "group": 11}, {"name": "obj_167", "group": 11}, {"name": "obj_178", "group": 11}, {"name": "obj_180", "group": 11}, {"name": "obj_63", "group": 12}, {"name": "obj_65", "group": 12}, {"name": "obj_66", "group": 12}, {"name": "obj_67", "group": 12}, {"name": "obj_73", "group": 12}, {"name": "obj_75", "group": 12}, {"name": "obj_77", "group": 12}, {"name": "obj_78", "group": 12}, {"name": "obj_79", "group": 12}, {"name": "obj_80", "group": 12}, {"name": "obj_82", "group": 12}, {"name": "obj_0", "group": 0}, {"name": "obj_1", "group": 0}, {"name": "obj_16", "group": 0}, {"name": "obj_42", "group": 0}, {"name": "obj_43", "group": 0}, {"name": "obj_45", "group": 0}, {"name": "obj_46", "group": 0}, {"name": "obj_50", "group": 0}, {"name": "obj_58", "group": 0}, {"name": "obj_84", "group": 0}, {"name": "obj_85", "group": 0}, {"name": "obj_92", "group": 0}, {"name": "obj_109", "group": 0}, {"name": "obj_110", "group": 0}, {"name": "obj_112", "group": 0}, {"name": "obj_113", "group": 0}, {"name": "obj_131", "group": 0}, {"name": "obj_152", "group": 0}, {"name": "obj_173", "group": 0}, {"name": "obj_175", "group": 0}, {"name": "obj_189", "group": 0}, {"name": "obj_190", "group": 0}, {"name": "obj_191", "group": 0}, {"name": "obj_47", "group": 1}, {"name": "obj_65", "group": 1}, {"name": "obj_66", "group": 1}, {"name": "obj_67", "group": 1}, {"name": "obj_72", "group": 1}, {"name": "obj_73", "group": 1}, {"name": "obj_79", "group": 1}, {"name": "obj_80", "group": 1}, {"name": "obj_82", "group": 1}, {"name": "obj_89", "group": 1}, {"name": "obj_27", "group": 2}, {"name": "obj_59", "group": 2}, {"name": "obj_60", "group": 2}, {"name": "obj_88", "group": 2}, {"name": "obj_90", "group": 2}, {"name": "obj_91", "group": 2}, {"name": "obj_93", "group": 2}, {"name": "obj_165", "group": 2}, {"name": "obj_32", "group": 3}, {"name": "obj_33", "group": 3}, {"name": "obj_34", "group": 3}, {"name": "obj_35", "group": 3}, {"name": "obj_36", "group": 3}, {"name": "obj_41", "group": 3}, {"name": "obj_63", "group": 3}, {"name": "obj_75", "group": 3}, {"name": "obj_76", "group": 3}, {"name": "obj_77", "group": 3}, {"name": "obj_78", "group": 3}, {"name": "obj_83", "group": 3}, {"name": "obj_70", "group": 4}, {"name": "obj_74", "group": 4}, {"name": "obj_99", "group": 4}, {"name": "obj_138", "group": 4}, {"name": "obj_139", "group": 4}, {"name": "obj_146", "group": 4}, {"name": "obj_159", "group": 4}, {"name": "obj_167", "group": 4}, {"name": "obj_178", "group": 4}, {"name": "obj_180", "group": 4}, {"name": "obj_4", "group": 5}, {"name": "obj_6", "group": 5}, {"name": "obj_9", "group": 5}, {"name": "obj_10", "group": 5}, {"name": "obj_17", "group": 5}, {"name": "obj_18", "group": 5}, {"name": "obj_19", "group": 5}, {"name": "obj_51", "group": 5}, {"name": "obj_52", "group": 5}, {"name": "obj_61", "group": 5}, {"name": "obj_62", "group": 5}, {"name": "obj_81", "group": 5}, {"name": "obj_94", "group": 5}, {"name": "obj_114", "group": 5}, {"name": "obj_115", "group": 5}, {"name": "obj_117", "group": 5}, {"name": "obj_124", "group": 5}, {"name": "obj_129", "group": 5}, {"name": "obj_143", "group": 5}, {"name": "obj_177", "group": 5}, {"name": "obj_187", "group": 5}, {"name": "obj_188", "group": 5}, {"name": "obj_198", "group": 5}, {"name": "obj_12", "group": 6}, {"name": "obj_13", "group": 6}, {"name": "obj_15", "group": 6}, {"name": "obj_20", "group": 6}, {"name": "obj_57", "group": 6}, {"name": "obj_95", "group": 6}, {"name": "obj_118", "group": 6}, {"name": "obj_119", "group": 6}, {"name": "obj_120", "group": 6}, {"name": "obj_137", "group": 6}, {"name": "obj_140", "group": 6}, {"name": "obj_160", "group": 6}, {"name": "obj_181", "group": 6}, {"name": "obj_182", "group": 6}, {"name": "obj_183", "group": 6}, {"name": "obj_204", "group": 6}, {"name": "obj_14", "group": 7}, {"name": "obj_54", "group": 7}, {"name": "obj_55", "group": 7}, {"name": "obj_56", "group": 7}, {"name": "obj_96", "group": 7}, {"name": "obj_97", "group": 7}, {"name": "obj_98", "group": 7}, {"name": "obj_104", "group": 7}, {"name": "obj_105", "group": 7}, {"name": "obj_106", "group": 7}, {"name": "obj_107", "group": 7}, {"name": "obj_116", "group": 7}, {"name": "obj_125", "group": 7}, {"name": "obj_141", "group": 7}, {"name": "obj_149", "group": 7}, {"name": "obj_150", "group": 7}, {"name": "obj_158", "group": 7}, {"name": "obj_161", "group": 7}, {"name": "obj_162", "group": 7}, {"name": "obj_169", "group": 7}, {"name": "obj_179", "group": 7}, {"name": "obj_199", "group": 7}, {"name": "obj_200", "group": 7}, {"name": "obj_201", "group": 7}, {"name": "obj_202", "group": 7}, {"name": "obj_203", "group": 7}, {"name": "obj_208", "group": 7}, {"name": "obj_209", "group": 7}, {"name": "obj_2", "group": 8}, {"name": "obj_44", "group": 8}, {"name": "obj_86", "group": 8}, {"name": "obj_87", "group": 8}, {"name": "obj_108", "group": 8}, {"name": "obj_121", "group": 8}, {"name": "obj_122", "group": 8}, {"name": "obj_123", "group": 8}, {"name": "obj_134", "group": 8}, {"name": "obj_164", "group": 8}, {"name": "obj_184", "group": 8}, {"name": "obj_192", "group": 8}, {"name": "obj_193", "group": 8}, {"name": "obj_205", "group": 8}, {"name": "obj_206", "group": 8}, {"name": "obj_207", "group": 8}, {"name": "obj_5", "group": 9}, {"name": "obj_7", "group": 9}, {"name": "obj_11", "group": 9}, {"name": "obj_48", "group": 9}, {"name": "obj_49", "group": 9}, {"name": "obj_53", "group": 9}, {"name": "obj_100", "group": 9}, {"name": "obj_111", "group": 9}, {"name": "obj_132", "group": 9}, {"name": "obj_133", "group": 9}, {"name": "obj_136", "group": 9}, {"name": "obj_153", "group": 9}, {"name": "obj_21", "group": 10}, {"name": "obj_22", "group": 10}, {"name": "obj_23", "group": 10}, {"name": "obj_24", "group": 10}, {"name": "obj_25", "group": 10}, {"name": "obj_28", "group": 10}, {"name": "obj_30", "group": 10}, {"name": "obj_31", "group": 10}, {"name": "obj_37", "group": 10}, {"name": "obj_38", "group": 10}, {"name": "obj_39", "group": 10}, {"name": "obj_40", "group": 10}, {"name": "obj_64", "group": 10}, {"name": "obj_101", "group": 10}, {"name": "obj_102", "group": 10}, {"name": "obj_128", "group": 10}, {"name": "obj_142", "group": 10}, {"name": "obj_163", "group": 10}, {"name": "obj_168", "group": 10}, {"name": "obj_170", "group": 10}, {"name": "obj_171", "group": 10}, {"name": "obj_172", "group": 10}, {"name": "obj_174", "group": 10}, {"name": "obj_176", "group": 10}, {"name": "obj_26", "group": 11}, {"name": "obj_29", "group": 11}, {"name": "obj_194", "group": 11}, {"name": "obj_195", "group": 11}, {"name": "obj_196", "group": 11}, {"name": "obj_197", "group": 11}, {"name": "obj_126", "group": 12}, {"name": "obj_127", "group": 12}, {"name": "obj_147", "group": 12}, {"name": "obj_148", "group": 12}, {"name": "obj_154", "group": 12}, {"name": "obj_155", "group": 12}, {"name": "obj_3", "group": 13}, {"name": "obj_8", "group": 13}, {"name": "obj_68", "group": 13}, {"name": "obj_69", "group": 13}, {"name": "obj_71", "group": 13}, {"name": "obj_103", "group": 13}, {"name": "obj_130", "group": 13}, {"name": "obj_135", "group": 13}, {"name": "obj_144", "group": 13}, {"name": "obj_145", "group": 13}, {"name": "obj_151", "group": 13}, {"name": "obj_156", "group": 13}, {"name": "obj_157", "group": 13}, {"name": "obj_166", "group": 13}, {"name": "obj_185", "group": 13}, {"name": "obj_186", "group": 13}], "links": [{"source": 0, "target": 1, "value": 2}, {"source": 0, "target": 42, "value": 2}, {"source": 0, "target": 43, "value": 2}, {"source": 0, "target": 84, "value": 2}, {"source": 0, "target": 86, "value": 2}, {"source": 0, "target": 131, "value": 2}, {"source": 1, "target": 42, "value": 1}, {"source": 1, "target": 101, "value": 2}, {"source": 1, "target": 173, "value": 2}, {"source": 1, "target": 176, "value": 2}, {"source": 2, "target": 44, "value": 1}, {"source": 2, "target": 107, "value": 2}, {"source": 2, "target": 108, "value": 3}, {"source": 2, "target": 121, "value": 2}, {"source": 2, "target": 205, "value": 1}, {"source": 3, "target": 8, "value": 3}, {"source": 3, "target": 16, "value": 2}, {"source": 3, "target": 68, "value": 1}, {"source": 3, "target": 71, "value": 2}, {"source": 3, "target": 151, "value": 5}, {"source": 3, "target": 156, "value": 2}, {"source": 4, "target": 17, "value": 3}, {"source": 4, "target": 81, "value": 1}, {"source": 4, "target": 114, "value": 2}, {"source": 4, "target": 115, "value": 1}, {"source": 4, "target": 198, "value": 1}, {"source": 5, "target": 7, "value": 5}, {"source": 5, "target": 8, "value": 1}, {"source": 5, "target": 11, "value": 2}, {"source": 5, "target": 92, "value": 2}, {"source": 5, "target": 100, "value": 1}, {"source": 5, "target": 109, "value": 2}, {"source": 5, "target": 113, "value": 2}, {"source": 6, "target": 10, "value": 1}, {"source": 6, "target": 49, "value": 1}, {"source": 6, "target": 52, "value": 1}, {"source": 6, "target": 115, "value": 1}, {"source": 6, "target": 124, "value": 2}, {"source": 7, "target": 11, "value": 2}, {"source": 7, "target": 92, "value": 1}, {"source": 7, "target": 100, "value": 2}, {"source": 7, "target": 109, "value": 1}, {"source": 8, "target": 16, "value": 3}, {"source": 8, "target": 109, "value": 1}, {"source": 8, "target": 151, "value": 1}, {"source": 9, "target": 10, "value": 18}, {"source": 9, "target": 18, "value": 6}, {"source": 9, "target": 19, "value": 2}, {"source": 9, "target": 115, "value": 2}, {"source": 9, "target": 124, "value": 3}, {"source": 9, "target": 177, "value": 3}, {"source": 9, "target": 187, "value": 2}, {"source": 10, "target": 18, "value": 4}, {"source": 10, "target": 19, "value": 3}, {"source": 10, "target": 70, "value": 1}, {"source": 10, "target": 115, "value": 2}, {"source": 10, "target": 124, "value": 4}, {"source": 10, "target": 177, "value": 2}, {"source": 10, "target": 187, "value": 2}, {"source": 11, "target": 48, "value": 1}, {"source": 11, "target": 100, "value": 2}, {"source": 11, "target": 133, "value": 1}, {"source": 12, "target": 13, "value": 4}, {"source": 12, "target": 15, "value": 2}, {"source": 12, "target": 19, "value": 3}, {"source": 12, "target": 20, "value": 6}, {"source": 12, "target": 182, "value": 2}, {"source": 13, "target": 15, "value": 29}, {"source": 13, "target": 20, "value": 9}, {"source": 13, "target": 120, "value": 6}, {"source": 13, "target": 182, "value": 7}, {"source": 13, "target": 183, "value": 7}, {"source": 14, "target": 45, "value": 2}, {"source": 14, "target": 105, "value": 3}, {"source": 14, "target": 106, "value": 4}, {"source": 14, "target": 112, "value": 1}, {"source": 14, "target": 116, "value": 2}, {"source": 14, "target": 175, "value": 2}, {"source": 14, "target": 179, "value": 2}, {"source": 14, "target": 202, "value": 2}, {"source": 15, "target": 20, "value": 5}, {"source": 15, "target": 120, "value": 9}, {"source": 15, "target": 140, "value": 7}, {"source": 15, "target": 182, "value": 8}, {"source": 15, "target": 183, "value": 10}, {"source": 16, "target": 43, "value": 1}, {"source": 16, "target": 84, "value": 1}, {"source": 16, "target": 85, "value": 1}, {"source": 17, "target": 18, "value": 1}, {"source": 17, "target": 114, "value": 1}, {"source": 17, "target": 143, "value": 1}, {"source": 17, "target": 198, "value": 2}, {"source": 18, "target": 19, "value": 2}, {"source": 18, "target": 81, "value": 1}, {"source": 18, "target": 177, "value": 6}, {"source": 18, "target": 198, "value": 1}, {"source": 19, "target": 177, "value": 2}, {"source": 20, "target": 182, "value": 3}, {"source": 20, "target": 183, "value": 3}, {"source": 21, "target": 22, "value": 5}, {"source": 21, "target": 25, "value": 7}, {"source": 21, "target": 28, "value": 2}, {"source": 21, "target": 30, "value": 7}, {"source": 21, "target": 38, "value": 4}, {"source": 21, "target": 39, "value": 6}, {"source": 21, "target": 64, "value": 2}, {"source": 22, "target": 25, "value": 2}, {"source": 22, "target": 29, "value": 2}, {"source": 22, "target": 30, "value": 3}, {"source": 22, "target": 39, "value": 2}, {"source": 22, "target": 64, "value": 2}, {"source": 23, "target": 24, "value": 6}, {"source": 23, "target": 31, "value": 6}, {"source": 23, "target": 32, "value": 4}, {"source": 23, "target": 33, "value": 4}, {"source": 23, "target": 37, "value": 6}, {"source": 23, "target": 40, "value": 4}, {"source": 23, "target": 169, "value": 2}, {"source": 24, "target": 28, "value": 2}, {"source": 24, "target": 30, "value": 4}, {"source": 24, "target": 31, "value": 7}, {"source": 24, "target": 37, "value": 16}, {"source": 24, "target": 40, "value": 6}, {"source": 25, "target": 37, "value": 3}, {"source": 25, "target": 38, "value": 7}, {"source": 25, "target": 39, "value": 3}, {"source": 25, "target": 64, "value": 3}, {"source": 25, "target": 168, "value": 3}, {"source": 25, "target": 171, "value": 2}, {"source": 25, "target": 176, "value": 2}, {"source": 26, "target": 29, "value": 2}, {"source": 26, "target": 42, "value": 2}, {"source": 26, "target": 43, "value": 2}, {"source": 26, "target": 50, "value": 2}, {"source": 26, "target": 101, "value": 1}, {"source": 26, "target": 131, "value": 2}, {"source": 26, "target": 194, "value": 1}, {"source": 26, "target": 195, "value": 1}, {"source": 27, "target": 90, "value": 1}, {"source": 27, "target": 102, "value": 1}, {"source": 27, "target": 165, "value": 1}, {"source": 27, "target": 196, "value": 1}, {"source": 27, "target": 200, "value": 1}, {"source": 28, "target": 31, "value": 3}, {"source": 28, "target": 37, "value": 2}, {"source": 28, "target": 38, "value": 2}, {"source": 28, "target": 40, "value": 2}, {"source": 29, "target": 194, "value": 3}, {"source": 29, "target": 195, "value": 2}, {"source": 29, "target": 197, "value": 1}, {"source": 30, "target": 37, "value": 4}, {"source": 30, "target": 39, "value": 3}, {"source": 30, "target": 40, "value": 3}, {"source": 31, "target": 32, "value": 4}, {"source": 31, "target": 37, "value": 7}, {"source": 31, "target": 40, "value": 7}, {"source": 32, "target": 33, "value": 16}, {"source": 32, "target": 34, "value": 6}, {"source": 32, "target": 35, "value": 7}, {"source": 32, "target": 36, "value": 6}, {"source": 32, "target": 40, "value": 4}, {"source": 32, "target": 41, "value": 9}, {"source": 33, "target": 34, "value": 9}, {"source": 33, "target": 35, "value": 9}, {"source": 33, "target": 36, "value": 9}, {"source": 33, "target": 41, "value": 14}, {"source": 34, "target": 35, "value": 19}, {"source": 34, "target": 36, "value": 17}, {"source": 34, "target": 41, "value": 26}, {"source": 34, "target": 78, "value": 3}, {"source": 35, "target": 36, "value": 19}, {"source": 35, "target": 41, "value": 15}, {"source": 35, "target": 63, "value": 2}, {"source": 35, "target": 77, "value": 2}, {"source": 35, "target": 78, "value": 4}, {"source": 35, "target": 83, "value": 2}, {"source": 36, "target": 41, "value": 13}, {"source": 37, "target": 38, "value": 2}, {"source": 37, "target": 39, "value": 3}, {"source": 37, "target": 40, "value": 4}, {"source": 37, "target": 169, "value": 2}, {"source": 38, "target": 39, "value": 3}, {"source": 39, "target": 64, "value": 3}, {"source": 39, "target": 171, "value": 1}, {"source": 42, "target": 43, "value": 33}, {"source": 42, "target": 50, "value": 3}, {"source": 42, "target": 84, "value": 7}, {"source": 42, "target": 85, "value": 5}, {"source": 42, "target": 92, "value": 2}, {"source": 42, "target": 110, "value": 6}, {"source": 42, "target": 131, "value": 9}, {"source": 42, "target": 152, "value": 6}, {"source": 42, "target": 173, "value": 5}, {"source": 42, "target": 176, "value": 1}, {"source": 42, "target": 189, "value": 2}, {"source": 43, "target": 50, "value": 3}, {"source": 43, "target": 84, "value": 10}, {"source": 43, "target": 85, "value": 9}, {"source": 43, "target": 110, "value": 4}, {"source": 43, "target": 131, "value": 5}, {"source": 43, "target": 152, "value": 3}, {"source": 43, "target": 173, "value": 3}, {"source": 43, "target": 189, "value": 2}, {"source": 44, "target": 86, "value": 3}, {"source": 44, "target": 121, "value": 2}, {"source": 44, "target": 123, "value": 2}, {"source": 44, "target": 134, "value": 3}, {"source": 44, "target": 184, "value": 2}, {"source": 45, "target": 46, "value": 2}, {"source": 45, "target": 48, "value": 1}, {"source": 45, "target": 50, "value": 1}, {"source": 45, "target": 58, "value": 4}, {"source": 45, "target": 85, "value": 2}, {"source": 46, "target": 50, "value": 2}, {"source": 46, "target": 58, "value": 2}, {"source": 46, "target": 85, "value": 2}, {"source": 46, "target": 148, "value": 2}, {"source": 46, "target": 155, "value": 2}, {"source": 47, "target": 66, "value": 2}, {"source": 47, "target": 67, "value": 2}, {"source": 47, "target": 73, "value": 1}, {"source": 47, "target": 80, "value": 1}, {"source": 47, "target": 89, "value": 2}, {"source": 48, "target": 49, "value": 1}, {"source": 48, "target": 111, "value": 2}, {"source": 48, "target": 136, "value": 1}, {"source": 48, "target": 153, "value": 1}, {"source": 49, "target": 53, "value": 11}, {"source": 49, "target": 132, "value": 2}, {"source": 49, "target": 133, "value": 2}, {"source": 49, "target": 136, "value": 2}, {"source": 49, "target": 153, "value": 2}, {"source": 50, "target": 58, "value": 2}, {"source": 50, "target": 84, "value": 2}, {"source": 50, "target": 85, "value": 2}, {"source": 50, "target": 92, "value": 2}, {"source": 50, "target": 113, "value": 2}, {"source": 50, "target": 131, "value": 2}, {"source": 51, "target": 52, "value": 3}, {"source": 51, "target": 62, "value": 2}, {"source": 51, "target": 94, "value": 2}, {"source": 51, "target": 114, "value": 1}, {"source": 51, "target": 117, "value": 2}, {"source": 51, "target": 129, "value": 3}, {"source": 51, "target": 143, "value": 3}, {"source": 52, "target": 61, "value": 3}, {"source": 52, "target": 62, "value": 6}, {"source": 52, "target": 94, "value": 2}, {"source": 52, "target": 117, "value": 3}, {"source": 52, "target": 129, "value": 8}, {"source": 52, "target": 143, "value": 3}, {"source": 52, "target": 188, "value": 2}, {"source": 53, "target": 54, "value": 1}, {"source": 53, "target": 82, "value": 1}, {"source": 53, "target": 132, "value": 1}, {"source": 53, "target": 133, "value": 3}, {"source": 53, "target": 136, "value": 1}, {"source": 54, "target": 56, "value": 4}, {"source": 54, "target": 96, "value": 3}, {"source": 54, "target": 97, "value": 7}, {"source": 54, "target": 136, "value": 2}, {"source": 54, "target": 149, "value": 4}, {"source": 54, "target": 150, "value": 3}, {"source": 54, "target": 153, "value": 3}, {"source": 55, "target": 56, "value": 6}, {"source": 55, "target": 96, "value": 6}, {"source": 55, "target": 97, "value": 8}, {"source": 55, "target": 98, "value": 5}, {"source": 55, "target": 157, "value": 2}, {"source": 55, "target": 158, "value": 5}, {"source": 56, "target": 97, "value": 14}, {"source": 56, "target": 98, "value": 12}, {"source": 56, "target": 104, "value": 5}, {"source": 56, "target": 125, "value": 3}, {"source": 56, "target": 141, "value": 12}, {"source": 56, "target": 161, "value": 9}, {"source": 56, "target": 162, "value": 11}, {"source": 57, "target": 95, "value": 5}, {"source": 57, "target": 118, "value": 2}, {"source": 57, "target": 119, "value": 4}, {"source": 57, "target": 120, "value": 26}, {"source": 57, "target": 137, "value": 5}, {"source": 57, "target": 140, "value": 54}, {"source": 57, "target": 160, "value": 15}, {"source": 57, "target": 181, "value": 6}, {"source": 57, "target": 182, "value": 12}, {"source": 57, "target": 183, "value": 20}, {"source": 57, "target": 204, "value": 9}, {"source": 58, "target": 84, "value": 2}, {"source": 58, "target": 85, "value": 2}, {"source": 59, "target": 60, "value": 1}, {"source": 59, "target": 87, "value": 3}, {"source": 59, "target": 88, "value": 2}, {"source": 59, "target": 90, "value": 2}, {"source": 59, "target": 92, "value": 2}, {"source": 59, "target": 164, "value": 2}, {"source": 59, "target": 165, "value": 2}, {"source": 60, "target": 90, "value": 2}, {"source": 60, "target": 91, "value": 1}, {"source": 60, "target": 92, "value": 1}, {"source": 60, "target": 155, "value": 1}, {"source": 61, "target": 62, "value": 4}, {"source": 61, "target": 94, "value": 3}, {"source": 61, "target": 117, "value": 3}, {"source": 61, "target": 129, "value": 3}, {"source": 61, "target": 143, "value": 2}, {"source": 62, "target": 117, "value": 9}, {"source": 62, "target": 129, "value": 5}, {"source": 62, "target": 188, "value": 5}, {"source": 62, "target": 208, "value": 2}, {"source": 63, "target": 75, "value": 4}, {"source": 63, "target": 77, "value": 5}, {"source": 63, "target": 78, "value": 6}, {"source": 63, "target": 83, "value": 2}, {"source": 64, "target": 102, "value": 1}, {"source": 64, "target": 128, "value": 1}, {"source": 64, "target": 142, "value": 1}, {"source": 64, "target": 168, "value": 2}, {"source": 65, "target": 66, "value": 5}, {"source": 65, "target": 67, "value": 3}, {"source": 65, "target": 73, "value": 5}, {"source": 65, "target": 79, "value": 21}, {"source": 65, "target": 80, "value": 3}, {"source": 66, "target": 67, "value": 13}, {"source": 66, "target": 73, "value": 6}, {"source": 66, "target": 79, "value": 6}, {"source": 66, "target": 80, "value": 6}, {"source": 66, "target": 89, "value": 2}, {"source": 67, "target": 72, "value": 1}, {"source": 67, "target": 73, "value": 5}, {"source": 67, "target": 79, "value": 4}, {"source": 67, "target": 80, "value": 7}, {"source": 67, "target": 82, "value": 1}, {"source": 67, "target": 89, "value": 2}, {"source": 68, "target": 69, "value": 2}, {"source": 68, "target": 71, "value": 17}, {"source": 68, "target": 151, "value": 2}, {"source": 68, "target": 156, "value": 2}, {"source": 69, "target": 71, "value": 2}, {"source": 69, "target": 103, "value": 2}, {"source": 69, "target": 151, "value": 2}, {"source": 69, "target": 156, "value": 2}, {"source": 70, "target": 74, "value": 6}, {"source": 70, "target": 146, "value": 1}, {"source": 70, "target": 178, "value": 2}, {"source": 70, "target": 180, "value": 1}, {"source": 71, "target": 151, "value": 2}, {"source": 71, "target": 156, "value": 1}, {"source": 72, "target": 73, "value": 1}, {"source": 72, "target": 81, "value": 5}, {"source": 72, "target": 82, "value": 5}, {"source": 72, "target": 133, "value": 1}, {"source": 72, "target": 172, "value": 1}, {"source": 73, "target": 79, "value": 6}, {"source": 73, "target": 80, "value": 4}, {"source": 73, "target": 82, "value": 3}, {"source": 74, "target": 146, "value": 2}, {"source": 74, "target": 159, "value": 2}, {"source": 74, "target": 178, "value": 3}, {"source": 74, "target": 180, "value": 3}, {"source": 75, "target": 76, "value": 3}, {"source": 75, "target": 77, "value": 12}, {"source": 75, "target": 78, "value": 12}, {"source": 75, "target": 83, "value": 4}, {"source": 76, "target": 77, "value": 2}, {"source": 76, "target": 78, "value": 2}, {"source": 76, "target": 83, "value": 22}, {"source": 76, "target": 119, "value": 2}, {"source": 77, "target": 78, "value": 20}, {"source": 77, "target": 83, "value": 2}, {"source": 78, "target": 83, "value": 3}, {"source": 79, "target": 80, "value": 4}, {"source": 80, "target": 89, "value": 2}, {"source": 81, "target": 82, "value": 2}, {"source": 81, "target": 198, "value": 1}, {"source": 82, "target": 133, "value": 1}, {"source": 84, "target": 85, "value": 49}, {"source": 84, "target": 131, "value": 3}, {"source": 84, "target": 189, "value": 3}, {"source": 84, "target": 190, "value": 2}, {"source": 85, "target": 131, "value": 2}, {"source": 85, "target": 189, "value": 2}, {"source": 85, "target": 190, "value": 1}, {"source": 86, "target": 87, "value": 2}, {"source": 86, "target": 122, "value": 4}, {"source": 86, "target": 123, "value": 3}, {"source": 86, "target": 184, "value": 3}, {"source": 86, "target": 192, "value": 4}, {"source": 86, "target": 193, "value": 2}, {"source": 87, "target": 88, "value": 2}, {"source": 87, "target": 164, "value": 2}, {"source": 87, "target": 205, "value": 2}, {"source": 87, "target": 206, "value": 2}, {"source": 88, "target": 93, "value": 2}, {"source": 88, "target": 143, "value": 1}, {"source": 88, "target": 165, "value": 1}, {"source": 89, "target": 152, "value": 1}, {"source": 90, "target": 91, "value": 3}, {"source": 90, "target": 93, "value": 3}, {"source": 90, "target": 165, "value": 2}, {"source": 91, "target": 93, "value": 2}, {"source": 91, "target": 111, "value": 2}, {"source": 91, "target": 174, "value": 2}, {"source": 92, "target": 110, "value": 2}, {"source": 92, "target": 131, "value": 2}, {"source": 92, "target": 152, "value": 2}, {"source": 93, "target": 143, "value": 2}, {"source": 93, "target": 165, "value": 2}, {"source": 93, "target": 198, "value": 2}, {"source": 94, "target": 130, "value": 3}, {"source": 94, "target": 143, "value": 2}, {"source": 95, "target": 137, "value": 7}, {"source": 95, "target": 140, "value": 4}, {"source": 95, "target": 160, "value": 4}, {"source": 95, "target": 182, "value": 3}, {"source": 96, "target": 97, "value": 5}, {"source": 96, "target": 98, "value": 3}, {"source": 96, "target": 136, "value": 2}, {"source": 96, "target": 153, "value": 3}, {"source": 96, "target": 154, "value": 2}, {"source": 96, "target": 157, "value": 2}, {"source": 97, "target": 98, "value": 7}, {"source": 97, "target": 104, "value": 5}, {"source": 97, "target": 149, "value": 9}, {"source": 97, "target": 150, "value": 3}, {"source": 97, "target": 158, "value": 5}, {"source": 97, "target": 161, "value": 8}, {"source": 98, "target": 104, "value": 7}, {"source": 98, "target": 141, "value": 5}, {"source": 99, "target": 138, "value": 4}, {"source": 99, "target": 139, "value": 11}, {"source": 99, "target": 146, "value": 13}, {"source": 99, "target": 159, "value": 15}, {"source": 99, "target": 167, "value": 3}, {"source": 99, "target": 178, "value": 3}, {"source": 99, "target": 180, "value": 11}, {"source": 100, "target": 133, "value": 1}, {"source": 100, "target": 172, "value": 2}, {"source": 101, "target": 102, "value": 4}, {"source": 101, "target": 171, "value": 1}, {"source": 101, "target": 176, "value": 1}, {"source": 102, "target": 163, "value": 2}, {"source": 102, "target": 168, "value": 1}, {"source": 102, "target": 174, "value": 2}, {"source": 103, "target": 145, "value": 3}, {"source": 103, "target": 151, "value": 2}, {"source": 103, "target": 156, "value": 3}, {"source": 103, "target": 157, "value": 2}, {"source": 103, "target": 166, "value": 2}, {"source": 104, "target": 141, "value": 4}, {"source": 104, "target": 162, "value": 4}, {"source": 105, "target": 106, "value": 5}, {"source": 105, "target": 141, "value": 4}, {"source": 105, "target": 161, "value": 4}, {"source": 105, "target": 162, "value": 4}, {"source": 105, "target": 179, "value": 6}, {"source": 106, "target": 116, "value": 7}, {"source": 106, "target": 161, "value": 5}, {"source": 106, "target": 162, "value": 5}, {"source": 106, "target": 169, "value": 2}, {"source": 106, "target": 179, "value": 13}, {"source": 107, "target": 121, "value": 5}, {"source": 107, "target": 141, "value": 2}, {"source": 107, "target": 161, "value": 2}, {"source": 107, "target": 162, "value": 2}, {"source": 108, "target": 121, "value": 2}, {"source": 108, "target": 122, "value": 3}, {"source": 108, "target": 184, "value": 2}, {"source": 108, "target": 205, "value": 2}, {"source": 109, "target": 110, "value": 2}, {"source": 109, "target": 112, "value": 1}, {"source": 109, "target": 113, "value": 4}, {"source": 109, "target": 152, "value": 2}, {"source": 109, "target": 175, "value": 2}, {"source": 109, "target": 191, "value": 1}, {"source": 110, "target": 113, "value": 2}, {"source": 110, "target": 131, "value": 15}, {"source": 110, "target": 152, "value": 54}, {"source": 110, "target": 173, "value": 25}, {"source": 111, "target": 132, "value": 2}, {"source": 111, "target": 136, "value": 2}, {"source": 111, "target": 153, "value": 4}, {"source": 111, "target": 174, "value": 2}, {"source": 111, "target": 191, "value": 1}, {"source": 112, "target": 113, "value": 2}, {"source": 112, "target": 116, "value": 2}, {"source": 112, "target": 175, "value": 4}, {"source": 112, "target": 191, "value": 1}, {"source": 113, "target": 175, "value": 2}, {"source": 113, "target": 190, "value": 1}, {"source": 114, "target": 115, "value": 1}, {"source": 114, "target": 117, "value": 1}, {"source": 115, "target": 117, "value": 3}, {"source": 115, "target": 124, "value": 6}, {"source": 115, "target": 187, "value": 3}, {"source": 116, "target": 141, "value": 4}, {"source": 116, "target": 161, "value": 4}, {"source": 116, "target": 162, "value": 4}, {"source": 116, "target": 179, "value": 8}, {"source": 117, "target": 129, "value": 4}, {"source": 117, "target": 188, "value": 2}, {"source": 117, "target": 208, "value": 2}, {"source": 118, "target": 120, "value": 2}, {"source": 118, "target": 140, "value": 2}, {"source": 118, "target": 183, "value": 2}, {"source": 118, "target": 188, "value": 5}, {"source": 119, "target": 120, "value": 4}, {"source": 119, "target": 160, "value": 5}, {"source": 119, "target": 181, "value": 5}, {"source": 119, "target": 183, "value": 4}, {"source": 120, "target": 140, "value": 45}, {"source": 120, "target": 160, "value": 8}, {"source": 120, "target": 182, "value": 21}, {"source": 120, "target": 183, "value": 83}, {"source": 120, "target": 204, "value": 8}, {"source": 121, "target": 123, "value": 2}, {"source": 121, "target": 134, "value": 2}, {"source": 121, "target": 184, "value": 3}, {"source": 122, "target": 123, "value": 7}, {"source": 122, "target": 164, "value": 2}, {"source": 122, "target": 184, "value": 5}, {"source": 122, "target": 192, "value": 3}, {"source": 122, "target": 205, "value": 3}, {"source": 122, "target": 206, "value": 2}, {"source": 123, "target": 134, "value": 2}, {"source": 123, "target": 164, "value": 4}, {"source": 123, "target": 184, "value": 4}, {"source": 123, "target": 205, "value": 2}, {"source": 124, "target": 177, "value": 1}, {"source": 124, "target": 187, "value": 3}, {"source": 125, "target": 141, "value": 4}, {"source": 125, "target": 158, "value": 3}, {"source": 125, "target": 161, "value": 3}, {"source": 125, "target": 162, "value": 4}, {"source": 125, "target": 188, "value": 2}, {"source": 126, "target": 127, "value": 24}, {"source": 126, "target": 147, "value": 11}, {"source": 126, "target": 148, "value": 15}, {"source": 126, "target": 154, "value": 2}, {"source": 126, "target": 155, "value": 4}, {"source": 127, "target": 147, "value": 16}, {"source": 127, "target": 148, "value": 9}, {"source": 127, "target": 154, "value": 2}, {"source": 127, "target": 155, "value": 5}, {"source": 128, "target": 142, "value": 6}, {"source": 128, "target": 163, "value": 6}, {"source": 128, "target": 168, "value": 3}, {"source": 128, "target": 170, "value": 4}, {"source": 129, "target": 130, "value": 2}, {"source": 129, "target": 143, "value": 4}, {"source": 130, "target": 135, "value": 2}, {"source": 130, "target": 143, "value": 3}, {"source": 130, "target": 144, "value": 2}, {"source": 130, "target": 186, "value": 1}, {"source": 131, "target": 152, "value": 20}, {"source": 131, "target": 173, "value": 12}, {"source": 132, "target": 136, "value": 4}, {"source": 132, "target": 145, "value": 2}, {"source": 132, "target": 153, "value": 3}, {"source": 134, "target": 154, "value": 2}, {"source": 134, "target": 164, "value": 2}, {"source": 135, "target": 144, "value": 6}, {"source": 135, "target": 145, "value": 2}, {"source": 135, "target": 156, "value": 2}, {"source": 135, "target": 166, "value": 3}, {"source": 135, "target": 185, "value": 2}, {"source": 135, "target": 186, "value": 2}, {"source": 136, "target": 153, "value": 3}, {"source": 136, "target": 200, "value": 1}, {"source": 137, "target": 140, "value": 4}, {"source": 137, "target": 160, "value": 6}, {"source": 137, "target": 181, "value": 4}, {"source": 138, "target": 146, "value": 4}, {"source": 138, "target": 159, "value": 5}, {"source": 138, "target": 167, "value": 3}, {"source": 138, "target": 180, "value": 3}, {"source": 139, "target": 146, "value": 5}, {"source": 139, "target": 159, "value": 6}, {"source": 139, "target": 167, "value": 2}, {"source": 139, "target": 180, "value": 4}, {"source": 140, "target": 160, "value": 9}, {"source": 140, "target": 181, "value": 5}, {"source": 140, "target": 182, "value": 18}, {"source": 140, "target": 183, "value": 49}, {"source": 140, "target": 204, "value": 9}, {"source": 141, "target": 149, "value": 6}, {"source": 141, "target": 161, "value": 36}, {"source": 141, "target": 162, "value": 169}, {"source": 141, "target": 179, "value": 8}, {"source": 141, "target": 202, "value": 3}, {"source": 141, "target": 203, "value": 2}, {"source": 141, "target": 209, "value": 5}, {"source": 142, "target": 163, "value": 3}, {"source": 142, "target": 168, "value": 3}, {"source": 142, "target": 170, "value": 2}, {"source": 143, "target": 198, "value": 1}, {"source": 144, "target": 156, "value": 3}, {"source": 144, "target": 166, "value": 4}, {"source": 144, "target": 185, "value": 1}, {"source": 144, "target": 186, "value": 2}, {"source": 145, "target": 156, "value": 2}, {"source": 145, "target": 157, "value": 2}, {"source": 145, "target": 165, "value": 1}, {"source": 146, "target": 159, "value": 35}, {"source": 146, "target": 167, "value": 8}, {"source": 146, "target": 178, "value": 3}, {"source": 146, "target": 180, "value": 14}, {"source": 147, "target": 148, "value": 13}, {"source": 147, "target": 154, "value": 2}, {"source": 147, "target": 155, "value": 5}, {"source": 148, "target": 154, "value": 2}, {"source": 148, "target": 155, "value": 3}, {"source": 149, "target": 158, "value": 7}, {"source": 149, "target": 161, "value": 9}, {"source": 149, "target": 162, "value": 7}, {"source": 149, "target": 169, "value": 2}, {"source": 150, "target": 158, "value": 3}, {"source": 150, "target": 161, "value": 3}, {"source": 150, "target": 162, "value": 3}, {"source": 151, "target": 156, "value": 9}, {"source": 151, "target": 166, "value": 2}, {"source": 152, "target": 173, "value": 29}, {"source": 153, "target": 157, "value": 1}, {"source": 153, "target": 174, "value": 2}, {"source": 153, "target": 200, "value": 1}, {"source": 154, "target": 158, "value": 2}, {"source": 156, "target": 166, "value": 3}, {"source": 156, "target": 185, "value": 1}, {"source": 158, "target": 161, "value": 7}, {"source": 158, "target": 162, "value": 5}, {"source": 159, "target": 167, "value": 7}, {"source": 159, "target": 178, "value": 3}, {"source": 159, "target": 180, "value": 11}, {"source": 160, "target": 181, "value": 14}, {"source": 160, "target": 183, "value": 7}, {"source": 161, "target": 162, "value": 78}, {"source": 161, "target": 179, "value": 8}, {"source": 162, "target": 179, "value": 8}, {"source": 162, "target": 202, "value": 3}, {"source": 162, "target": 203, "value": 2}, {"source": 162, "target": 209, "value": 5}, {"source": 163, "target": 168, "value": 2}, {"source": 163, "target": 170, "value": 2}, {"source": 163, "target": 174, "value": 1}, {"source": 164, "target": 165, "value": 3}, {"source": 166, "target": 187, "value": 1}, {"source": 167, "target": 180, "value": 3}, {"source": 168, "target": 171, "value": 2}, {"source": 169, "target": 179, "value": 2}, {"source": 170, "target": 184, "value": 3}, {"source": 170, "target": 192, "value": 2}, {"source": 170, "target": 193, "value": 2}, {"source": 171, "target": 172, "value": 1}, {"source": 171, "target": 176, "value": 2}, {"source": 172, "target": 176, "value": 1}, {"source": 172, "target": 185, "value": 2}, {"source": 173, "target": 176, "value": 2}, {"source": 175, "target": 190, "value": 1}, {"source": 178, "target": 180, "value": 9}, {"source": 181, "target": 182, "value": 7}, {"source": 182, "target": 183, "value": 22}, {"source": 182, "target": 204, "value": 6}, {"source": 183, "target": 204, "value": 7}, {"source": 184, "target": 192, "value": 3}, {"source": 184, "target": 193, "value": 3}, {"source": 184, "target": 205, "value": 3}, {"source": 185, "target": 186, "value": 1}, {"source": 186, "target": 207, "value": 1}, {"source": 189, "target": 190, "value": 5}, {"source": 191, "target": 197, "value": 1}, {"source": 191, "target": 206, "value": 1}, {"source": 192, "target": 193, "value": 7}, {"source": 192, "target": 205, "value": 7}, {"source": 192, "target": 206, "value": 3}, {"source": 192, "target": 207, "value": 1}, {"source": 193, "target": 205, "value": 4}, {"source": 193, "target": 206, "value": 3}, {"source": 193, "target": 207, "value": 2}, {"source": 194, "target": 195, "value": 6}, {"source": 194, "target": 196, "value": 3}, {"source": 194, "target": 197, "value": 4}, {"source": 195, "target": 196, "value": 2}, {"source": 195, "target": 197, "value": 2}, {"source": 196, "target": 197, "value": 1}, {"source": 196, "target": 200, "value": 2}, {"source": 199, "target": 200, "value": 1}, {"source": 199, "target": 201, "value": 3}, {"source": 199, "target": 202, "value": 2}, {"source": 199, "target": 203, "value": 2}, {"source": 199, "target": 208, "value": 2}, {"source": 199, "target": 209, "value": 1}, {"source": 200, "target": 203, "value": 2}, {"source": 201, "target": 202, "value": 8}, {"source": 201, "target": 203, "value": 6}, {"source": 201, "target": 208, "value": 2}, {"source": 201, "target": 209, "value": 9}, {"source": 202, "target": 203, "value": 19}, {"source": 202, "target": 208, "value": 2}, {"source": 202, "target": 209, "value": 12}, {"source": 203, "target": 209, "value": 8}, {"source": 205, "target": 206, "value": 5}, {"source": 205, "target": 207, "value": 1}, {"source": 206, "target": 207, "value": 2}]}